carry_lookahead_adder/full_adder.vhd
library ieee;
use ieee.std_logic_1164.all;
use ieee.numeric_std.all;

entity full_adder is
    port(
        --inputs
        i_bit_1: in std_logic;
        i_bit_0: in std_logic;
        i_carry: in std_logic;
        --outputs
        o_sum: out std_logic;
        o_carry: out std_logic
        );
end full_adder;

architecture arch of full_adder is
begin
        o_sum <= i_bit_1 xor i_bit_0 xor i_carry;
        o_carry <= (i_bit_1 and i_bit_0) or ((i_bit_1 xor i_bit_0) and i_carry);
end arch;

carry_lookahead_adder/carry_lookahead_adder.vhd
library ieee;
use ieee.std_logic_1164.all;

entity carry_lookahead_adder is
    generic(
        g_width: natural := 2
    );
    port(
        --inputs
        i_num_1: in std_logic_vector(g_width-1 downto 0);
        i_num_0: in std_logic_vector(g_width-1 downto 0);
        --outputs
        o_result: out std_logic_vector(g_width downto 0)
    );
end carry_lookahead_adder;

architecture arch of carry_lookahead_adder is
    component full_adder is
        port(
            i_bit_1: in std_logic;
            i_bit_0: in std_logic;
            i_carry: in std_logic;
            o_sum: out std_logic;
            o_carry: out std_logic
        );
    end component full_adder;

    signal w_generate: std_logic_vector(g_width-1 downto 0);
    signal w_propagate: std_logic_vector(g_width-1 downto 0);
    signal w_carry: std_logic_vector(g_width downto 0);

    signal w_sum: std_logic_vector(g_width-1 downto 0);

begin
    generate_full_adders: for i in 0 to g_width-1 generate
        inst_full_adder: full_adder port map(
            i_bit_1 => i_num_1(i),
            i_bit_0 => i_num_0(i),
            i_carry => w_carry(i),
            o_sum => w_sum(i),
            o_carry => open
        );
    end generate generate_full_adders;

    generate_carry_lookahead_adders: for j in 0 to g_width-1 generate
        w_generate(j) <= i_num_1(j) and i_num_0(j);
        w_propagate(j) <= (i_num_1(j) or i_num_0(j)) and w_carry(j);
        w_carry(j+1) <= w_generate(j) or w_propagate(j);
    end generate generate_carry_lookahead_adders;

    --no carry input for first carry lookahead adder
    w_carry(0) <= '0';

    o_result <= w_carry(g_width) & w_sum;
end arch;

carry_lookahead_adder/carry_lookahead_adder_tb.vhd
library ieee;
use ieee.std_logic_1164.all;

entity carry_lookahead_adder_tb is
end carry_lookahead_adder_tb;

architecture testbench of carry_lookahead_adder_tb is
    constant c_width: integer := 3;

    signal r_num_1: std_logic_vector(c_width-1 downto 0) := (others => '0');
    signal r_num_0: std_logic_vector(c_width-1 downto 0) := (others => '0');
    signal r_result: std_logic_vector(c_width downto 0);

    component carry_lookahead_adder is
        generic(
            g_width: natural
        );
        port(
            i_num_1: in std_logic_vector(g_width-1 downto 0);
            i_num_0: in std_logic_vector(g_width-1 downto 0);
            o_result: out std_logic_vector(g_width downto 0)
        );
    end component carry_lookahead_adder;

begin
    UUT: carry_lookahead_adder
        generic map(
            g_width => c_width
        )
        port map(
            i_num_1 => r_num_1,
            i_num_0 => r_num_0,
            o_result => r_result
        );

    process begin
        r_num_1 <= "000";
        r_num_0 <= "001";
        wait for 10 ns;
        r_num_1 <= "100";
        r_num_0 <= "011";
        wait for 10 ns;
        r_num_1 <= "010";
        r_num_0 <= "101";
        wait for 10 ns;
        r_num_1 <= "111";
        r_num_0 <= "111";
        wait for 10 ns;
    end process;
end testbench;

carry_lookahead_adder/carry_lookahead_adder_wave.vcd
$date
  Wed Dec 29 13:12:00 2021
$end
$version
  GHDL v0
$end
$timescale
  1 fs
$end
$scope module standard $end
$upscope $end
$scope module std_logic_1164 $end
$upscope $end
$scope module numeric_std $end
$upscope $end
$scope module carry_lookahead_adder_tb $end
$var reg 3 ! r_num_1[2:0] $end
$var reg 3 " r_num_0[2:0] $end
$var reg 4 # r_result[3:0] $end
$scope module uut $end
$var reg 3 $ i_num_1[2:0] $end
$var reg 3 % i_num_0[2:0] $end
$var reg 4 & o_result[3:0] $end
$var reg 3 ' w_generate[2:0] $end
$var reg 3 ( w_propagate[2:0] $end
$var reg 4 ) w_carry[3:0] $end
$var reg 3 * w_sum[2:0] $end
$scope module generate_full_adders(0) $end
$scope module inst_full_adder $end
$var reg 1 + i_bit_1 $end
$var reg 1 , i_bit_0 $end
$var reg 1 - i_carry $end
$var reg 1 . o_sum $end
$var reg 1 / o_carry $end
$upscope $end
$upscope $end
$scope module generate_full_adders(1) $end
$scope module inst_full_adder $end
$var reg 1 0 i_bit_1 $end
$var reg 1 1 i_bit_0 $end
$var reg 1 2 i_carry $end
$var reg 1 3 o_sum $end
$var reg 1 4 o_carry $end
$upscope $end
$upscope $end
$scope module generate_full_adders(2) $end
$scope module inst_full_adder $end
$var reg 1 5 i_bit_1 $end
$var reg 1 6 i_bit_0 $end
$var reg 1 7 i_carry $end
$var reg 1 8 o_sum $end
$var reg 1 9 o_carry $end
$upscope $end
$upscope $end
$scope module generate_carry_lookahead_adders(0) $end
$upscope $end
$scope module generate_carry_lookahead_adders(1) $end
$upscope $end
$scope module generate_carry_lookahead_adders(2) $end
$upscope $end
$upscope $end
$upscope $end
$enddefinitions $end
#0
b000 !
b001 "
b0001 #
b000 $
b001 %
b0001 &
b000 '
b000 (
b0000 )
b001 *
0+
1,
0-
1.
0/
00
01
02
03
04
05
06
07
08
09
#10000000
b100 !
b011 "
b0111 #
b100 $
b011 %
b0111 &
b111 *
11
13
15
18
#20000000
b010 !
b101 "
b010 $
b101 %
10
01
05
16
#30000000
b111 !
b111 "
b1110 #
b111 $
b111 %
b1110 &
b111 '
b110 (
b1110 )
b110 *
1+
0.
1/
11
12
13
14
15
17
18
19
#40000000
b000 !
b001 "
b0001 #
b000 $
b001 %
b0001 &
b000 '
b000 (
b0000 )
b001 *
0+
1.
0/
00
01
02
03
04
05
06
07
08
09
#50000000
b100 !
b011 "
b0111 #
b100 $
b011 %
b0111 &
b111 *
11
13
15
18
#60000000
b010 !
b101 "
b010 $
b101 %
10
01
05
16
#70000000
b111 !
b111 "
b1110 #
b111 $
b111 %
b1110 &
b111 '
b110 (
b1110 )
b110 *
1+
0.
1/
11
12
13
14
15
17
18
19
#80000000
b000 !
b001 "
b0001 #
b000 $
b001 %
b0001 &
b000 '
b000 (
b0000 )
b001 *
0+
1.
0/
00
01
02
03
04
05
06
07
08
09
#90000000
b100 !
b011 "
b0111 #
b100 $
b011 %
b0111 &
b111 *
11
13
15
18
#100000000
b010 !
b101 "
b010 $
b101 %
10
01
05
16
#110000000
b111 !
b111 "
b1110 #
b111 $
b111 %
b1110 &
b111 '
b110 (
b1110 )
b110 *
1+
0.
1/
11
12
13
14
15
17
18
19
#120000000
b000 !
b001 "
b0001 #
b000 $
b001 %
b0001 &
b000 '
b000 (
b0000 )
b001 *
0+
1.
0/
00
01
02
03
04
05
06
07
08
09
#130000000
b100 !
b011 "
b0111 #
b100 $
b011 %
b0111 &
b111 *
11
13
15
18
#140000000
b010 !
b101 "
b010 $
b101 %
10
01
05
16
#150000000
b111 !
b111 "
b1110 #
b111 $
b111 %
b1110 &
b111 '
b110 (
b1110 )
b110 *
1+
0.
1/
11
12
13
14
15
17
18
19
#160000000
b000 !
b001 "
b0001 #
b000 $
b001 %
b0001 &
b000 '
b000 (
b0000 )
b001 *
0+
1.
0/
00
01
02
03
04
05
06
07
08
09
#170000000
b100 !
b011 "
b0111 #
b100 $
b011 %
b0111 &
b111 *
11
13
15
18
#180000000
b010 !
b101 "
b010 $
b101 %
10
01
05
16
#190000000
b111 !
b111 "
b1110 #
b111 $
b111 %
b1110 &
b111 '
b110 (
b1110 )
b110 *
1+
0.
1/
11
12
13
14
15
17
18
19
#200000000
b000 !
b001 "
b0001 #
b000 $
b001 %
b0001 &
b000 '
b000 (
b0000 )
b001 *
0+
1.
0/
00
01
02
03
04
05
06
07
08
09
#210000000
b100 !
b011 "
b0111 #
b100 $
b011 %
b0111 &
b111 *
11
13
15
18
#220000000
b010 !
b101 "
b010 $
b101 %
10
01
05
16
#230000000
b111 !
b111 "
b1110 #
b111 $
b111 %
b1110 &
b111 '
b110 (
b1110 )
b110 *
1+
0.
1/
11
12
13
14
15
17
18
19
#240000000
b000 !
b001 "
b0001 #
b000 $
b001 %
b0001 &
b000 '
b000 (
b0000 )
b001 *
0+
1.
0/
00
01
02
03
04
05
06
07
08
09
#250000000
b100 !
b011 "
b0111 #
b100 $
b011 %
b0111 &
b111 *
11
13
15
18
#260000000
b010 !
b101 "
b010 $
b101 %
10
01
05
16
#270000000
b111 !
b111 "
b1110 #
b111 $
b111 %
b1110 &
b111 '
b110 (
b1110 )
b110 *
1+
0.
1/
11
12
13
14
15
17
18
19
#280000000
b000 !
b001 "
b0001 #
b000 $
b001 %
b0001 &
b000 '
b000 (
b0000 )
b001 *
0+
1.
0/
00
01
02
03
04
05
06
07
08
09
#290000000
b100 !
b011 "
b0111 #
b100 $
b011 %
b0111 &
b111 *
11
13
15
18
#300000000
b010 !
b101 "
b010 $
b101 %
10
01
05
16
#310000000
b111 !
b111 "
b1110 #
b111 $
b111 %
b1110 &
b111 '
b110 (
b1110 )
b110 *
1+
0.
1/
11
12
13
14
15
17
18
19
#320000000
b000 !
b001 "
b0001 #
b000 $
b001 %
b0001 &
b000 '
b000 (
b0000 )
b001 *
0+
1.
0/
00
01
02
03
04
05
06
07
08
09
#330000000
b100 !
b011 "
b0111 #
b100 $
b011 %
b0111 &
b111 *
11
13
15
18
#340000000
b010 !
b101 "
b010 $
b101 %
10
01
05
16
#350000000
b111 !
b111 "
b1110 #
b111 $
b111 %
b1110 &
b111 '
b110 (
b1110 )
b110 *
1+
0.
1/
11
12
13
14
15
17
18
19
#360000000
b000 !
b001 "
b0001 #
b000 $
b001 %
b0001 &
b000 '
b000 (
b0000 )
b001 *
0+
1.
0/
00
01
02
03
04
05
06
07
08
09
#370000000
b100 !
b011 "
b0111 #
b100 $
b011 %
b0111 &
b111 *
11
13
15
18
#380000000
b010 !
b101 "
b010 $
b101 %
10
01
05
16
#390000000
b111 !
b111 "
b1110 #
b111 $
b111 %
b1110 &
b111 '
b110 (
b1110 )
b110 *
1+
0.
1/
11
12
13
14
15
17
18
19
#400000000
b000 !
b001 "
b0001 #
b000 $
b001 %
b0001 &
b000 '
b000 (
b0000 )
b001 *
0+
1.
0/
00
01
02
03
04
05
06
07
08
09
#410000000
b100 !
b011 "
b0111 #
b100 $
b011 %
b0111 &
b111 *
11
13
15
18
#420000000
b010 !
b101 "
b010 $
b101 %
10
01
05
16
#430000000
b111 !
b111 "
b1110 #
b111 $
b111 %
b1110 &
b111 '
b110 (
b1110 )
b110 *
1+
0.
1/
11
12
13
14
15
17
18
19
#440000000
b000 !
b001 "
b0001 #
b000 $
b001 %
b0001 &
b000 '
b000 (
b0000 )
b001 *
0+
1.
0/
00
01
02
03
04
05
06
07
08
09
#450000000
b100 !
b011 "
b0111 #
b100 $
b011 %
b0111 &
b111 *
11
13
15
18
#460000000
b010 !
b101 "
b010 $
b101 %
10
01
05
16
#470000000
b111 !
b111 "
b1110 #
b111 $
b111 %
b1110 &
b111 '
b110 (
b1110 )
b110 *
1+
0.
1/
11
12
13
14
15
17
18
19
#480000000
b000 !
b001 "
b0001 #
b000 $
b001 %
b0001 &
b000 '
b000 (
b0000 )
b001 *
0+
1.
0/
00
01
02
03
04
05
06
07
08
09
#490000000
b100 !
b011 "
b0111 #
b100 $
b011 %
b0111 &
b111 *
11
13
15
18
#500000000
b010 !
b101 "
b010 $
b101 %
10
01
05
16
#510000000
b111 !
b111 "
b1110 #
b111 $
b111 %
b1110 &
b111 '
b110 (
b1110 )
b110 *
1+
0.
1/
11
12
13
14
15
17
18
19
#520000000
b000 !
b001 "
b0001 #
b000 $
b001 %
b0001 &
b000 '
b000 (
b0000 )
b001 *
0+
1.
0/
00
01
02
03
04
05
06
07
08
09
#530000000
b100 !
b011 "
b0111 #
b100 $
b011 %
b0111 &
b111 *
11
13
15
18
#540000000
b010 !
b101 "
b010 $
b101 %
10
01
05
16
#550000000
b111 !
b111 "
b1110 #
b111 $
b111 %
b1110 &
b111 '
b110 (
b1110 )
b110 *
1+
0.
1/
11
12
13
14
15
17
18
19
#560000000
b000 !
b001 "
b0001 #
b000 $
b001 %
b0001 &
b000 '
b000 (
b0000 )
b001 *
0+
1.
0/
00
01
02
03
04
05
06
07
08
09
#570000000
b100 !
b011 "
b0111 #
b100 $
b011 %
b0111 &
b111 *
11
13
15
18
#580000000
b010 !
b101 "
b010 $
b101 %
10
01
05
16
#590000000
b111 !
b111 "
b1110 #
b111 $
b111 %
b1110 &
b111 '
b110 (
b1110 )
b110 *
1+
0.
1/
11
12
13
14
15
17
18
19
#600000000
b000 !
b001 "
b0001 #
b000 $
b001 %
b0001 &
b000 '
b000 (
b0000 )
b001 *
0+
1.
0/
00
01
02
03
04
05
06
07
08
09
#610000000
b100 !
b011 "
b0111 #
b100 $
b011 %
b0111 &
b111 *
11
13
15
18
#620000000
b010 !
b101 "
b010 $
b101 %
10
01
05
16
#630000000
b111 !
b111 "
b1110 #
b111 $
b111 %
b1110 &
b111 '
b110 (
b1110 )
b110 *
1+
0.
1/
11
12
13
14
15
17
18
19
#640000000
b000 !
b001 "
b0001 #
b000 $
b001 %
b0001 &
b000 '
b000 (
b0000 )
b001 *
0+
1.
0/
00
01
02
03
04
05
06
07
08
09
#650000000
b100 !
b011 "
b0111 #
b100 $
b011 %
b0111 &
b111 *
11
13
15
18
#660000000
b010 !
b101 "
b010 $
b101 %
10
01
05
16
#670000000
b111 !
b111 "
b1110 #
b111 $
b111 %
b1110 &
b111 '
b110 (
b1110 )
b110 *
1+
0.
1/
11
12
13
14
15
17
18
19
#680000000
b000 !
b001 "
b0001 #
b000 $
b001 %
b0001 &
b000 '
b000 (
b0000 )
b001 *
0+
1.
0/
00
01
02
03
04
05
06
07
08
09
#690000000
b100 !
b011 "
b0111 #
b100 $
b011 %
b0111 &
b111 *
11
13
15
18
#700000000
b010 !
b101 "
b010 $
b101 %
10
01
05
16
#710000000
b111 !
b111 "
b1110 #
b111 $
b111 %
b1110 &
b111 '
b110 (
b1110 )
b110 *
1+
0.
1/
11
12
13
14
15
17
18
19
#720000000
b000 !
b001 "
b0001 #
b000 $
b001 %
b0001 &
b000 '
b000 (
b0000 )
b001 *
0+
1.
0/
00
01
02
03
04
05
06
07
08
09
#730000000
b100 !
b011 "
b0111 #
b100 $
b011 %
b0111 &
b111 *
11
13
15
18
#740000000
b010 !
b101 "
b010 $
b101 %
10
01
05
16
#750000000
b111 !
b111 "
b1110 #
b111 $
b111 %
b1110 &
b111 '
b110 (
b1110 )
b110 *
1+
0.
1/
11
12
13
14
15
17
18
19
#760000000
b000 !
b001 "
b0001 #
b000 $
b001 %
b0001 &
b000 '
b000 (
b0000 )
b001 *
0+
1.
0/
00
01
02
03
04
05
06
07
08
09
#770000000
b100 !
b011 "
b0111 #
b100 $
b011 %
b0111 &
b111 *
11
13
15
18
#780000000
b010 !
b101 "
b010 $
b101 %
10
01
05
16
#790000000
b111 !
b111 "
b1110 #
b111 $
b111 %
b1110 &
b111 '
b110 (
b1110 )
b110 *
1+
0.
1/
11
12
13
14
15
17
18
19
#800000000
b000 !
b001 "
b0001 #
b000 $
b001 %
b0001 &
b000 '
b000 (
b0000 )
b001 *
0+
1.
0/
00
01
02
03
04
05
06
07
08
09
#810000000
b100 !
b011 "
b0111 #
b100 $
b011 %
b0111 &
b111 *
11
13
15
18
#820000000
b010 !
b101 "
b010 $
b101 %
10
01
05
16
#830000000
b111 !
b111 "
b1110 #
b111 $
b111 %
b1110 &
b111 '
b110 (
b1110 )
b110 *
1+
0.
1/
11
12
13
14
15
17
18
19
#840000000
b000 !
b001 "
b0001 #
b000 $
b001 %
b0001 &
b000 '
b000 (
b0000 )
b001 *
0+
1.
0/
00
01
02
03
04
05
06
07
08
09
#850000000
b100 !
b011 "
b0111 #
b100 $
b011 %
b0111 &
b111 *
11
13
15
18
#860000000
b010 !
b101 "
b010 $
b101 %
10
01
05
16
#870000000
b111 !
b111 "
b1110 #
b111 $
b111 %
b1110 &
b111 '
b110 (
b1110 )
b110 *
1+
0.
1/
11
12
13
14
15
17
18
19
#880000000
b000 !
b001 "
b0001 #
b000 $
b001 %
b0001 &
b000 '
b000 (
b0000 )
b001 *
0+
1.
0/
00
01
02
03
04
05
06
07
08
09
#890000000
b100 !
b011 "
b0111 #
b100 $
b011 %
b0111 &
b111 *
11
13
15
18
#900000000
b010 !
b101 "
b010 $
b101 %
10
01
05
16
#910000000
b111 !
b111 "
b1110 #
b111 $
b111 %
b1110 &
b111 '
b110 (
b1110 )
b110 *
1+
0.
1/
11
12
13
14
15
17
18
19
#920000000
b000 !
b001 "
b0001 #
b000 $
b001 %
b0001 &
b000 '
b000 (
b0000 )
b001 *
0+
1.
0/
00
01
02
03
04
05
06
07
08
09
#930000000
b100 !
b011 "
b0111 #
b100 $
b011 %
b0111 &
b111 *
11
13
15
18
#940000000
b010 !
b101 "
b010 $
b101 %
10
01
05
16
#950000000
b111 !
b111 "
b1110 #
b111 $
b111 %
b1110 &
b111 '
b110 (
b1110 )
b110 *
1+
0.
1/
11
12
13
14
15
17
18
19
#960000000
b000 !
b001 "
b0001 #
b000 $
b001 %
b0001 &
b000 '
b000 (
b0000 )
b001 *
0+
1.
0/
00
01
02
03
04
05
06
07
08
09
#970000000
b100 !
b011 "
b0111 #
b100 $
b011 %
b0111 &
b111 *
11
13
15
18
#980000000
b010 !
b101 "
b010 $
b101 %
10
01
05
16
#990000000
b111 !
b111 "
b1110 #
b111 $
b111 %
b1110 &
b111 '
b110 (
b1110 )
b110 *
1+
0.
1/
11
12
13
14
15
17
18
19
#1000000000
b000 !
b001 "
b0001 #
b000 $
b001 %
b0001 &
b000 '
b000 (
b0000 )
b001 *
0+
1.
0/
00
01
02
03
04
05
06
07
08
09
#1010000000
b100 !
b011 "
b0111 #
b100 $
b011 %
b0111 &
b111 *
11
13
15
18
#1020000000
b010 !
b101 "
b010 $
b101 %
10
01
05
16
#1030000000
b111 !
b111 "
b1110 #
b111 $
b111 %
b1110 &
b111 '
b110 (
b1110 )
b110 *
1+
0.
1/
11
12
13
14
15
17
18
19
#1040000000
b000 !
b001 "
b0001 #
b000 $
b001 %
b0001 &
b000 '
b000 (
b0000 )
b001 *
0+
1.
0/
00
01
02
03
04
05
06
07
08
09
#1050000000
b100 !
b011 "
b0111 #
b100 $
b011 %
b0111 &
b111 *
11
13
15
18
#1060000000
b010 !
b101 "
b010 $
b101 %
10
01
05
16
#1070000000
b111 !
b111 "
b1110 #
b111 $
b111 %
b1110 &
b111 '
b110 (
b1110 )
b110 *
1+
0.
1/
11
12
13
14
15
17
18
19
#1080000000
b000 !
b001 "
b0001 #
b000 $
b001 %
b0001 &
b000 '
b000 (
b0000 )
b001 *
0+
1.
0/
00
01
02
03
04
05
06
07
08
09
#1090000000
b100 !
b011 "
b0111 #
b100 $
b011 %
b0111 &
b111 *
11
13
15
18
#1100000000
b010 !
b101 "
b010 $
b101 %
10
01
05
16
#1110000000
b111 !
b111 "
b1110 #
b111 $
b111 %
b1110 &
b111 '
b110 (
b1110 )
b110 *
1+
0.
1/
11
12
13
14
15
17
18
19
#1120000000
b000 !
b001 "
b0001 #
b000 $
b001 %
b0001 &
b000 '
b000 (
b0000 )
b001 *
0+
1.
0/
00
01
02
03
04
05
06
07
08
09
#1130000000
b100 !
b011 "
b0111 #
b100 $
b011 %
b0111 &
b111 *
11
13
15
18
#1140000000
b010 !
b101 "
b010 $
b101 %
10
01
05
16
#1150000000
b111 !
b111 "
b1110 #
b111 $
b111 %
b1110 &
b111 '
b110 (
b1110 )
b110 *
1+
0.
1/
11
12
13
14
15
17
18
19
#1160000000
b000 !
b001 "
b0001 #
b000 $
b001 %
b0001 &
b000 '
b000 (
b0000 )
b001 *
0+
1.
0/
00
01
02
03
04
05
06
07
08
09
#1170000000
b100 !
b011 "
b0111 #
b100 $
b011 %
b0111 &
b111 *
11
13
15
18
#1180000000
b010 !
b101 "
b010 $
b101 %
10
01
05
16
#1190000000
b111 !
b111 "
b1110 #
b111 $
b111 %
b1110 &
b111 '
b110 (
b1110 )
b110 *
1+
0.
1/
11
12
13
14
15
17
18
19
#1200000000
b000 !
b001 "
b0001 #
b000 $
b001 %
b0001 &
b000 '
b000 (
b0000 )
b001 *
0+
1.
0/
00
01
02
03
04
05
06
07
08
09
#1210000000
b100 !
b011 "
b0111 #
b100 $
b011 %
b0111 &
b111 *
11
13
15
18
#1220000000
b010 !
b101 "
b010 $
b101 %
10
01
05
16
#1230000000
b111 !
b111 "
b1110 #
b111 $
b111 %
b1110 &
b111 '
b110 (
b1110 )
b110 *
1+
0.
1/
11
12
13
14
15
17
18
19
#1240000000
b000 !
b001 "
b0001 #
b000 $
b001 %
b0001 &
b000 '
b000 (
b0000 )
b001 *
0+
1.
0/
00
01
02
03
04
05
06
07
08
09
#1250000000
b100 !
b011 "
b0111 #
b100 $
b011 %
b0111 &
b111 *
11
13
15
18
#1260000000
b010 !
b101 "
b010 $
b101 %
10
01
05
16
#1270000000
b111 !
b111 "
b1110 #
b111 $
b111 %
b1110 &
b111 '
b110 (
b1110 )
b110 *
1+
0.
1/
11
12
13
14
15
17
18
19
#1280000000
b000 !
b001 "
b0001 #
b000 $
b001 %
b0001 &
b000 '
b000 (
b0000 )
b001 *
0+
1.
0/
00
01
02
03
04
05
06
07
08
09
#1290000000
b100 !
b011 "
b0111 #
b100 $
b011 %
b0111 &
b111 *
11
13
15
18
#1300000000
b010 !
b101 "
b010 $
b101 %
10
01
05
16
#1310000000
b111 !
b111 "
b1110 #
b111 $
b111 %
b1110 &
b111 '
b110 (
b1110 )
b110 *
1+
0.
1/
11
12
13
14
15
17
18
19
#1320000000
b000 !
b001 "
b0001 #
b000 $
b001 %
b0001 &
b000 '
b000 (
b0000 )
b001 *
0+
1.
0/
00
01
02
03
04
05
06
07
08
09
#1330000000
b100 !
b011 "
b0111 #
b100 $
b011 %
b0111 &
b111 *
11
13
15
18
#1340000000
b010 !
b101 "
b010 $
b101 %
10
01
05
16
#1350000000
b111 !
b111 "
b1110 #
b111 $
b111 %
b1110 &
b111 '
b110 (
b1110 )
b110 *
1+
0.
1/
11
12
13
14
15
17
18
19
#1360000000
b000 !
b001 "
b0001 #
b000 $
b001 %
b0001 &
b000 '
b000 (
b0000 )
b001 *
0+
1.
0/
00
01
02
03
04
05
06
07
08
09
#1370000000
b100 !
b011 "
b0111 #
b100 $
b011 %
b0111 &
b111 *
11
13
15
18
#1380000000
b010 !
b101 "
b010 $
b101 %
10
01
05
16
#1390000000
b111 !
b111 "
b1110 #
b111 $
b111 %
b1110 &
b111 '
b110 (
b1110 )
b110 *
1+
0.
1/
11
12
13
14
15
17
18
19
#1400000000
b000 !
b001 "
b0001 #
b000 $
b001 %
b0001 &
b000 '
b000 (
b0000 )
b001 *
0+
1.
0/
00
01
02
03
04
05
06
07
08
09
#1410000000
b100 !
b011 "
b0111 #
b100 $
b011 %
b0111 &
b111 *
11
13
15
18
#1420000000
b010 !
b101 "
b010 $
b101 %
10
01
05
16
#1430000000
b111 !
b111 "
b1110 #
b111 $
b111 %
b1110 &
b111 '
b110 (
b1110 )
b110 *
1+
0.
1/
11
12
13
14
15
17
18
19
#1440000000
b000 !
b001 "
b0001 #
b000 $
b001 %
b0001 &
b000 '
b000 (
b0000 )
b001 *
0+
1.
0/
00
01
02
03
04
05
06
07
08
09
#1450000000
b100 !
b011 "
b0111 #
b100 $
b011 %
b0111 &
b111 *
11
13
15
18
#1460000000
b010 !
b101 "
b010 $
b101 %
10
01
05
16
#1470000000
b111 !
b111 "
b1110 #
b111 $
b111 %
b1110 &
b111 '
b110 (
b1110 )
b110 *
1+
0.
1/
11
12
13
14
15
17
18
19
#1480000000
b000 !
b001 "
b0001 #
b000 $
b001 %
b0001 &
b000 '
b000 (
b0000 )
b001 *
0+
1.
0/
00
01
02
03
04
05
06
07
08
09
#1490000000
b100 !
b011 "
b0111 #
b100 $
b011 %
b0111 &
b111 *
11
13
15
18
#1500000000
b010 !
b101 "
b010 $
b101 %
10
01
05
16
#1510000000
b111 !
b111 "
b1110 #
b111 $
b111 %
b1110 &
b111 '
b110 (
b1110 )
b110 *
1+
0.
1/
11
12
13
14
15
17
18
19
#1520000000
b000 !
b001 "
b0001 #
b000 $
b001 %
b0001 &
b000 '
b000 (
b0000 )
b001 *
0+
1.
0/
00
01
02
03
04
05
06
07
08
09
#1530000000
b100 !
b011 "
b0111 #
b100 $
b011 %
b0111 &
b111 *
11
13
15
18
#1540000000
b010 !
b101 "
b010 $
b101 %
10
01
05
16
#1550000000
b111 !
b111 "
b1110 #
b111 $
b111 %
b1110 &
b111 '
b110 (
b1110 )
b110 *
1+
0.
1/
11
12
13
14
15
17
18
19
#1560000000
b000 !
b001 "
b0001 #
b000 $
b001 %
b0001 &
b000 '
b000 (
b0000 )
b001 *
0+
1.
0/
00
01
02
03
04
05
06
07
08
09
#1570000000
b100 !
b011 "
b0111 #
b100 $
b011 %
b0111 &
b111 *
11
13
15
18
#1580000000
b010 !
b101 "
b010 $
b101 %
10
01
05
16
#1590000000
b111 !
b111 "
b1110 #
b111 $
b111 %
b1110 &
b111 '
b110 (
b1110 )
b110 *
1+
0.
1/
11
12
13
14
15
17
18
19
#1600000000
b000 !
b001 "
b0001 #
b000 $
b001 %
b0001 &
b000 '
b000 (
b0000 )
b001 *
0+
1.
0/
00
01
02
03
04
05
06
07
08
09
#1610000000
b100 !
b011 "
b0111 #
b100 $
b011 %
b0111 &
b111 *
11
13
15
18
#1620000000
b010 !
b101 "
b010 $
b101 %
10
01
05
16
#1630000000
b111 !
b111 "
b1110 #
b111 $
b111 %
b1110 &
b111 '
b110 (
b1110 )
b110 *
1+
0.
1/
11
12
13
14
15
17
18
19
#1640000000
b000 !
b001 "
b0001 #
b000 $
b001 %
b0001 &
b000 '
b000 (
b0000 )
b001 *
0+
1.
0/
00
01
02
03
04
05
06
07
08
09
#1650000000
b100 !
b011 "
b0111 #
b100 $
b011 %
b0111 &
b111 *
11
13
15
18
#1660000000
b010 !
b101 "
b010 $
b101 %
10
01
05
16
#1670000000
b111 !
b111 "
b1110 #
b111 $
b111 %
b1110 &
b111 '
b110 (
b1110 )
b110 *
1+
0.
1/
11
12
13
14
15
17
18
19
#1680000000
b000 !
b001 "
b0001 #
b000 $
b001 %
b0001 &
b000 '
b000 (
b0000 )
b001 *
0+
1.
0/
00
01
02
03
04
05
06
07
08
09
#1690000000
b100 !
b011 "
b0111 #
b100 $
b011 %
b0111 &
b111 *
11
13
15
18
#1700000000
b010 !
b101 "
b010 $
b101 %
10
01
05
16
#1710000000
b111 !
b111 "
b1110 #
b111 $
b111 %
b1110 &
b111 '
b110 (
b1110 )
b110 *
1+
0.
1/
11
12
13
14
15
17
18
19
#1720000000
b000 !
b001 "
b0001 #
b000 $
b001 %
b0001 &
b000 '
b000 (
b0000 )
b001 *
0+
1.
0/
00
01
02
03
04
05
06
07
08
09
#1730000000
b100 !
b011 "
b0111 #
b100 $
b011 %
b0111 &
b111 *
11
13
15
18
#1740000000
b010 !
b101 "
b010 $
b101 %
10
01
05
16
#1750000000
b111 !
b111 "
b1110 #
b111 $
b111 %
b1110 &
b111 '
b110 (
b1110 )
b110 *
1+
0.
1/
11
12
13
14
15
17
18
19
#1760000000
b000 !
b001 "
b0001 #
b000 $
b001 %
b0001 &
b000 '
b000 (
b0000 )
b001 *
0+
1.
0/
00
01
02
03
04
05
06
07
08
09
#1770000000
b100 !
b011 "
b0111 #
b100 $
b011 %
b0111 &
b111 *
11
13
15
18
#1780000000
b010 !
b101 "
b010 $
b101 %
10
01
05
16
#1790000000
b111 !
b111 "
b1110 #
b111 $
b111 %
b1110 &
b111 '
b110 (
b1110 )
b110 *
1+
0.
1/
11
12
13
14
15
17
18
19
#1800000000
b000 !
b001 "
b0001 #
b000 $
b001 %
b0001 &
b000 '
b000 (
b0000 )
b001 *
0+
1.
0/
00
01
02
03
04
05
06
07
08
09
#1810000000
b100 !
b011 "
b0111 #
b100 $
b011 %
b0111 &
b111 *
11
13
15
18
#1820000000
b010 !
b101 "
b010 $
b101 %
10
01
05
16
#1830000000
b111 !
b111 "
b1110 #
b111 $
b111 %
b1110 &
b111 '
b110 (
b1110 )
b110 *
1+
0.
1/
11
12
13
14
15
17
18
19
#1840000000
b000 !
b001 "
b0001 #
b000 $
b001 %
b0001 &
b000 '
b000 (
b0000 )
b001 *
0+
1.
0/
00
01
02
03
04
05
06
07
08
09
#1850000000
b100 !
b011 "
b0111 #
b100 $
b011 %
b0111 &
b111 *
11
13
15
18
#1860000000
b010 !
b101 "
b010 $
b101 %
10
01
05
16
#1870000000
b111 !
b111 "
b1110 #
b111 $
b111 %
b1110 &
b111 '
b110 (
b1110 )
b110 *
1+
0.
1/
11
12
13
14
15
17
18
19
#1880000000
b000 !
b001 "
b0001 #
b000 $
b001 %
b0001 &
b000 '
b000 (
b0000 )
b001 *
0+
1.
0/
00
01
02
03
04
05
06
07
08
09
#1890000000
b100 !
b011 "
b0111 #
b100 $
b011 %
b0111 &
b111 *
11
13
15
18
#1900000000
b010 !
b101 "
b010 $
b101 %
10
01
05
16
#1910000000
b111 !
b111 "
b1110 #
b111 $
b111 %
b1110 &
b111 '
b110 (
b1110 )
b110 *
1+
0.
1/
11
12
13
14
15
17
18
19
#1920000000
b000 !
b001 "
b0001 #
b000 $
b001 %
b0001 &
b000 '
b000 (
b0000 )
b001 *
0+
1.
0/
00
01
02
03
04
05
06
07
08
09
#1930000000
b100 !
b011 "
b0111 #
b100 $
b011 %
b0111 &
b111 *
11
13
15
18
#1940000000
b010 !
b101 "
b010 $
b101 %
10
01
05
16
#1950000000
b111 !
b111 "
b1110 #
b111 $
b111 %
b1110 &
b111 '
b110 (
b1110 )
b110 *
1+
0.
1/
11
12
13
14
15
17
18
19
