fifo_register/fifo_register.vhd
library ieee;
use ieee.std_logic_1164.all;

entity fifo_register is 
    generic(
        g_word_size: positive := 8;
        g_depth: positive := 32
    );
    port(
        --input
        i_clk: in std_logic;
        i_rst: in std_logic;
        i_write_en: in std_logic;
        i_read_en: in std_logic;
        i_write_data: in std_logic_vector(g_word_size-1 downto 0);
        --output
        o_fifo_full: out std_logic;
        o_fifo_empty: out std_logic;
        o_read_data: out std_logic_vector(g_word_size-1 downto 0)
    );
end fifo_register;

architecture arch of fifo_register is
    type t_fifo_data is array(0 to g_depth-1) of std_logic_vector(g_word_size-1 downto 0);
    signal r_fifo_data: t_fifo_data := (others => (others => '0'));

    signal r_write_pointer: integer range 0 to g_depth-1 := 0;
    signal r_read_pointer: integer range 0 to g_depth-1 := 0;

    signal r_fifo_count: integer := 0;

    signal w_fifo_full: std_logic;
    signal w_fifo_empty: std_logic;

begin
    p_main: process(i_clk)
    begin
        if rising_edge(i_clk) then
            if (i_rst = '1') then
                r_fifo_count <= 0;
                r_write_pointer <= 0;
                r_read_pointer <= 0;
            else
                -- count fifo words
                if (i_write_en = '1' and i_read_en = '0') then
                    r_fifo_count <= r_fifo_count+1;
                elsif (i_write_en ='0' and i_read_en = '1') then
                    r_fifo_count <= r_fifo_count-1;
                end if;

                -- manage fifo write pointer
                if (i_write_en = '1' and w_fifo_full = '0') then
                    if (r_write_pointer = g_depth-1) then
                        r_write_pointer <= 0;
                    else
                        r_write_pointer <= r_write_pointer+1;
                    end if;
                end if;
                    
                -- manage fifo read pointer
                if (i_read_en = '1' and w_fifo_empty = '0') then
                    if (r_read_pointer = g_depth-1) then
                        r_read_pointer <= 0;
                    else
                        r_read_pointer <= r_read_pointer+1;
                    end if;
                end if;

                -- write data
                if (i_write_en = '1') then
                    r_fifo_data(r_write_pointer) <= i_write_data;
                end if;
            end if;
        end if;
    end process p_main;
    
    o_read_data <= r_fifo_data(r_read_pointer);

    w_fifo_full <= '1' when r_fifo_count = g_depth else '0';
    w_fifo_empty <= '1' when r_fifo_count = 0 else '0';

    o_fifo_full <= w_fifo_full;
    o_fifo_empty <= w_fifo_empty;

    p_assert: process(i_clk)
    begin
        if rising_edge(i_clk) then
            if (i_write_en = '1' and w_fifo_full = '1') then
                report "error: fifo is full, but it being written" severity failure;
            end if;
                
            if (i_read_en = '1' and w_fifo_empty = '1') then
                report "error: fifo empty, but is being read";
            end if;
        end if;
    end process p_assert;
end arch;

fifo_register/fifo_register_tb.vhd
library ieee;
use ieee.std_logic_1164.all;
use ieee.numeric_std.all;

entity fifo_register_tb is
end fifo_register_tb;

architecture testbench of fifo_register_tb is
    constant c_word_size: integer := 8;
    constant c_depth: integer := 4;
   
    signal r_clk: std_logic := '0';
    signal r_rst: std_logic := '0';
    signal r_write_en: std_logic := '0';
    signal r_read_en: std_logic := '0';
    signal r_write_data: std_logic_vector(c_word_size-1 downto 0) := X"DE";

    signal w_fifo_full: std_logic;
    signal w_fifo_empty: std_logic;
    signal w_read_data: std_logic_vector(c_word_size-1 downto 0);

    component fifo_register is
        generic(
            g_word_size: positive := 8;
            g_depth: positive := 32
        );
        port(
            --input
            i_clk: in std_logic;
            i_rst: in std_logic;
            i_write_en: in std_logic;
            i_read_en: in std_logic;
            i_write_data: in std_logic_vector(g_word_size-1 downto 0);
            --output
            o_fifo_full: out std_logic;
            o_fifo_empty: out std_logic;
            o_read_data: out std_logic_vector(g_word_size-1 downto 0)
        );
    end component fifo_register;

begin
    UUT: fifo_register
        generic map(
            g_word_size => c_word_size,
            g_depth => c_depth
        )
        port map(
            i_clk => r_clk,
            i_rst => r_rst,
            i_write_en => r_write_en,
            i_read_en => r_read_en,
            i_write_data => r_write_data,
            o_fifo_full => w_fifo_full,
            o_fifo_empty => w_fifo_empty,
            o_read_data => w_read_data
        );
    
    r_clk <= not r_clk after 5 ns;

    p_test: process
    begin
        wait until r_clk = '1';
        r_write_en <= '1';
        wait until r_clk = '1';
        wait until r_clk = '1';
        wait until r_clk = '1';
        r_write_en <= '0';
        r_read_en <= '1';
        wait until r_clk = '1';
        wait until r_clk = '1';
        wait until r_clk = '1';
        wait until r_clk = '1';
        r_read_en <= '0';
        r_write_en <= '1';
        wait until r_clk = '1';
        wait until r_clk = '1';
        r_write_en <= '0';
        r_read_en <= '1';
        wait until r_clk = '1';
        wait until r_clk = '1';
        wait until r_clk = '1';
        wait until r_clk = '1';
        wait until r_clk = '1';
        wait until r_clk = '1';
        wait until r_clk = '1';
        wait until r_clk = '1';
        r_read_en <= '0';
        wait until r_clk = '1';
        wait until r_clk = '1';
        wait until r_clk = '1';
        wait until r_clk = '1';
    end process;
end testbench;

fifo_register/fifo_register_wave.vcd
$date
  Thu Dec 30 18:33:14 2021
$end
$version
  GHDL v0
$end
$timescale
  1 fs
$end
$scope module standard $end
$upscope $end
$scope module std_logic_1164 $end
$upscope $end
$scope module numeric_std $end
$upscope $end
$scope module fifo_register_tb $end
$var reg 1 ! r_clk $end
$var reg 1 " r_rst $end
$var reg 1 # r_write_en $end
$var reg 1 $ r_read_en $end
$var reg 8 % r_write_data[7:0] $end
$var reg 1 & w_fifo_full $end
$var reg 1 ' w_fifo_empty $end
$var reg 8 ( w_read_data[7:0] $end
$scope module uut $end
$var reg 1 ) i_clk $end
$var reg 1 * i_rst $end
$var reg 1 + i_write_en $end
$var reg 1 , i_read_en $end
$var reg 8 - i_write_data[7:0] $end
$var reg 1 . o_fifo_full $end
$var reg 1 / o_fifo_empty $end
$var reg 8 0 o_read_data[7:0] $end
$comment r_fifo_data is not handled $end
$var integer 32 1 r_write_pointer $end
$var integer 32 2 r_read_pointer $end
$var integer 32 3 r_fifo_count $end
$var reg 1 4 w_fifo_full $end
$var reg 1 5 w_fifo_empty $end
$upscope $end
$upscope $end
$enddefinitions $end
#0
0!
0"
0#
0$
b11011110 %
0&
1'
b00000000 (
0)
0*
0+
0,
b11011110 -
0.
1/
b00000000 0
b0 1
b0 2
b0 3
04
15
#5000000
1!
1#
1)
1+
#10000000
0!
0)
#15000000
1!
0'
b11011110 (
1)
0/
b11011110 0
b1 1
b1 3
05
#20000000
0!
0)
#25000000
1!
1)
b10 1
b10 3
#30000000
0!
0)
#35000000
1!
0#
1$
1)
0+
1,
b11 1
b11 3
#40000000
0!
0)
#45000000
1!
1)
b1 2
b10 3
#50000000
0!
0)
#55000000
1!
1)
b10 2
b1 3
#60000000
0!
0)
#65000000
1!
1'
b00000000 (
1)
1/
b00000000 0
b11 2
b0 3
15
#70000000
0!
0)
#75000000
1!
1#
0$
0'
1)
1+
0,
0/
b11111111111111111111111111111111 3
05
#80000000
0!
0)
#85000000
1!
1'
b11011110 (
1)
1/
b11011110 0
b0 1
b0 3
15
#90000000
0!
0)
#95000000
1!
0#
1$
0'
1)
0+
1,
0/
b1 1
b1 3
05
#100000000
0!
0)
#105000000
1!
1'
1)
1/
b0 2
b0 3
15
#110000000
0!
0)
#115000000
1!
0'
1)
0/
b11111111111111111111111111111111 3
05
#120000000
0!
0)
#125000000
1!
1)
b1 2
b11111111111111111111111111111110 3
#130000000
0!
0)
#135000000
1!
1)
b10 2
b11111111111111111111111111111101 3
#140000000
0!
0)
#145000000
1!
1)
b11 2
b11111111111111111111111111111100 3
#150000000
0!
0)
#155000000
1!
1)
b0 2
b11111111111111111111111111111011 3
#160000000
0!
0)
#165000000
1!
1)
b1 2
b11111111111111111111111111111010 3
#170000000
0!
0)
#175000000
1!
0$
1)
0,
b10 2
b11111111111111111111111111111001 3
#180000000
0!
0)
#185000000
1!
1)
#190000000
0!
0)
#195000000
1!
1)
#200000000
0!
0)
#205000000
1!
1)
#210000000
0!
0)
#215000000
1!
1)
#220000000
0!
0)
#225000000
1!
1#
1)
1+
#230000000
0!
0)
#235000000
1!
1)
b10 1
b11111111111111111111111111111010 3
#240000000
0!
0)
#245000000
1!
1)
b11 1
b11111111111111111111111111111011 3
#250000000
0!
0)
#255000000
1!
0#
1$
1)
0+
1,
b0 1
b11111111111111111111111111111100 3
#260000000
0!
0)
#265000000
1!
1)
b11 2
b11111111111111111111111111111011 3
#270000000
0!
0)
#275000000
1!
1)
b0 2
b11111111111111111111111111111010 3
#280000000
0!
0)
#285000000
1!
1)
b1 2
b11111111111111111111111111111001 3
#290000000
0!
0)
#295000000
1!
1#
0$
1)
1+
0,
b10 2
b11111111111111111111111111111000 3
#300000000
0!
0)
#305000000
1!
1)
b1 1
b11111111111111111111111111111001 3
#310000000
0!
0)
#315000000
1!
0#
1$
1)
0+
1,
b10 1
b11111111111111111111111111111010 3
#320000000
0!
0)
#325000000
1!
1)
b11 2
b11111111111111111111111111111001 3
#330000000
0!
0)
#335000000
1!
1)
b0 2
b11111111111111111111111111111000 3
#340000000
0!
0)
#345000000
1!
1)
b1 2
b11111111111111111111111111110111 3
#350000000
0!
0)
#355000000
1!
1)
b10 2
b11111111111111111111111111110110 3
#360000000
0!
0)
#365000000
1!
1)
b11 2
b11111111111111111111111111110101 3
#370000000
0!
0)
#375000000
1!
1)
b0 2
b11111111111111111111111111110100 3
#380000000
0!
0)
#385000000
1!
1)
b1 2
b11111111111111111111111111110011 3
#390000000
0!
0)
#395000000
1!
0$
1)
0,
b10 2
b11111111111111111111111111110010 3
#400000000
0!
0)
#405000000
1!
1)
#410000000
0!
0)
#415000000
1!
1)
#420000000
0!
0)
#425000000
1!
1)
#430000000
0!
0)
#435000000
1!
1)
#440000000
0!
0)
#445000000
1!
1#
1)
1+
#450000000
0!
0)
#455000000
1!
1)
b11 1
b11111111111111111111111111110011 3
#460000000
0!
0)
#465000000
1!
1)
b0 1
b11111111111111111111111111110100 3
#470000000
0!
0)
#475000000
1!
0#
1$
1)
0+
1,
b1 1
b11111111111111111111111111110101 3
#480000000
0!
0)
#485000000
1!
1)
b11 2
b11111111111111111111111111110100 3
#490000000
0!
0)
#495000000
1!
1)
b0 2
b11111111111111111111111111110011 3
#500000000
0!
0)
#505000000
1!
1)
b1 2
b11111111111111111111111111110010 3
#510000000
0!
0)
#515000000
1!
1#
0$
1)
1+
0,
b10 2
b11111111111111111111111111110001 3
#520000000
0!
0)
#525000000
1!
1)
b10 1
b11111111111111111111111111110010 3
#530000000
0!
0)
#535000000
1!
0#
1$
1)
0+
1,
b11 1
b11111111111111111111111111110011 3
#540000000
0!
0)
#545000000
1!
1)
b11 2
b11111111111111111111111111110010 3
#550000000
0!
0)
#555000000
1!
1)
b0 2
b11111111111111111111111111110001 3
#560000000
0!
0)
#565000000
1!
1)
b1 2
b11111111111111111111111111110000 3
#570000000
0!
0)
#575000000
1!
1)
b10 2
b11111111111111111111111111101111 3
#580000000
0!
0)
#585000000
1!
1)
b11 2
b11111111111111111111111111101110 3
#590000000
0!
0)
#595000000
1!
1)
b0 2
b11111111111111111111111111101101 3
#600000000
0!
0)
#605000000
1!
1)
b1 2
b11111111111111111111111111101100 3
#610000000
0!
0)
#615000000
1!
0$
1)
0,
b10 2
b11111111111111111111111111101011 3
#620000000
0!
0)
#625000000
1!
1)
#630000000
0!
0)
#635000000
1!
1)
#640000000
0!
0)
#645000000
1!
1)
#650000000
0!
0)
#655000000
1!
1)
#660000000
0!
0)
#665000000
1!
1#
1)
1+
#670000000
0!
0)
#675000000
1!
1)
b0 1
b11111111111111111111111111101100 3
#680000000
0!
0)
#685000000
1!
1)
b1 1
b11111111111111111111111111101101 3
#690000000
0!
0)
#695000000
1!
0#
1$
1)
0+
1,
b10 1
b11111111111111111111111111101110 3
#700000000
0!
0)
#705000000
1!
1)
b11 2
b11111111111111111111111111101101 3
#710000000
0!
0)
#715000000
1!
1)
b0 2
b11111111111111111111111111101100 3
#720000000
0!
0)
#725000000
1!
1)
b1 2
b11111111111111111111111111101011 3
#730000000
0!
0)
#735000000
1!
1#
0$
1)
1+
0,
b10 2
b11111111111111111111111111101010 3
#740000000
0!
0)
#745000000
1!
1)
b11 1
b11111111111111111111111111101011 3
#750000000
0!
0)
#755000000
1!
0#
1$
1)
0+
1,
b0 1
b11111111111111111111111111101100 3
#760000000
0!
0)
#765000000
1!
1)
b11 2
b11111111111111111111111111101011 3
#770000000
0!
0)
#775000000
1!
1)
b0 2
b11111111111111111111111111101010 3
#780000000
0!
0)
#785000000
1!
1)
b1 2
b11111111111111111111111111101001 3
#790000000
0!
0)
#795000000
1!
1)
b10 2
b11111111111111111111111111101000 3
#800000000
0!
0)
#805000000
1!
1)
b11 2
b11111111111111111111111111100111 3
#810000000
0!
0)
#815000000
1!
1)
b0 2
b11111111111111111111111111100110 3
#820000000
0!
0)
#825000000
1!
1)
b1 2
b11111111111111111111111111100101 3
#830000000
0!
0)
#835000000
1!
0$
1)
0,
b10 2
b11111111111111111111111111100100 3
#840000000
0!
0)
#845000000
1!
1)
#850000000
0!
0)
#855000000
1!
1)
#860000000
0!
0)
#865000000
1!
1)
#870000000
0!
0)
#875000000
1!
1)
#880000000
0!
0)
#885000000
1!
1#
1)
1+
#890000000
0!
0)
#895000000
1!
1)
b1 1
b11111111111111111111111111100101 3
#900000000
0!
0)
#905000000
1!
1)
b10 1
b11111111111111111111111111100110 3
#910000000
0!
0)
#915000000
1!
0#
1$
1)
0+
1,
b11 1
b11111111111111111111111111100111 3
#920000000
0!
0)
#925000000
1!
1)
b11 2
b11111111111111111111111111100110 3
#930000000
0!
0)
#935000000
1!
1)
b0 2
b11111111111111111111111111100101 3
#940000000
0!
0)
#945000000
1!
1)
b1 2
b11111111111111111111111111100100 3
#950000000
0!
0)
#955000000
1!
1#
0$
1)
1+
0,
b10 2
b11111111111111111111111111100011 3
#960000000
0!
0)
#965000000
1!
1)
b0 1
b11111111111111111111111111100100 3
#970000000
0!
0)
#975000000
1!
0#
1$
1)
0+
1,
b1 1
b11111111111111111111111111100101 3
#980000000
0!
0)
#985000000
1!
1)
b11 2
b11111111111111111111111111100100 3
#990000000
0!
0)
#995000000
1!
1)
b0 2
b11111111111111111111111111100011 3
#1000000000
0!
0)
#1005000000
1!
1)
b1 2
b11111111111111111111111111100010 3
#1010000000
0!
0)
#1015000000
1!
1)
b10 2
b11111111111111111111111111100001 3
#1020000000
0!
0)
#1025000000
1!
1)
b11 2
b11111111111111111111111111100000 3
#1030000000
0!
0)
#1035000000
1!
1)
b0 2
b11111111111111111111111111011111 3
#1040000000
0!
0)
#1045000000
1!
1)
b1 2
b11111111111111111111111111011110 3
#1050000000
0!
0)
#1055000000
1!
0$
1)
0,
b10 2
b11111111111111111111111111011101 3
#1060000000
0!
0)
#1065000000
1!
1)
#1070000000
0!
0)
#1075000000
1!
1)
#1080000000
0!
0)
#1085000000
1!
1)
#1090000000
0!
0)
#1095000000
1!
1)
#1100000000
0!
0)
#1105000000
1!
1#
1)
1+
#1110000000
0!
0)
#1115000000
1!
1)
b10 1
b11111111111111111111111111011110 3
#1120000000
0!
0)
#1125000000
1!
1)
b11 1
b11111111111111111111111111011111 3
#1130000000
0!
0)
#1135000000
1!
0#
1$
1)
0+
1,
b0 1
b11111111111111111111111111100000 3
#1140000000
0!
0)
#1145000000
1!
1)
b11 2
b11111111111111111111111111011111 3
#1150000000
0!
0)
#1155000000
1!
1)
b0 2
b11111111111111111111111111011110 3
#1160000000
0!
0)
#1165000000
1!
1)
b1 2
b11111111111111111111111111011101 3
#1170000000
0!
0)
#1175000000
1!
1#
0$
1)
1+
0,
b10 2
b11111111111111111111111111011100 3
#1180000000
0!
0)
#1185000000
1!
1)
b1 1
b11111111111111111111111111011101 3
#1190000000
0!
0)
#1195000000
1!
0#
1$
1)
0+
1,
b10 1
b11111111111111111111111111011110 3
#1200000000
0!
0)
#1205000000
1!
1)
b11 2
b11111111111111111111111111011101 3
#1210000000
0!
0)
#1215000000
1!
1)
b0 2
b11111111111111111111111111011100 3
#1220000000
0!
0)
#1225000000
1!
1)
b1 2
b11111111111111111111111111011011 3
#1230000000
0!
0)
#1235000000
1!
1)
b10 2
b11111111111111111111111111011010 3
#1240000000
0!
0)
#1245000000
1!
1)
b11 2
b11111111111111111111111111011001 3
#1250000000
0!
0)
#1255000000
1!
1)
b0 2
b11111111111111111111111111011000 3
#1260000000
0!
0)
#1265000000
1!
1)
b1 2
b11111111111111111111111111010111 3
#1270000000
0!
0)
#1275000000
1!
0$
1)
0,
b10 2
b11111111111111111111111111010110 3
#1280000000
0!
0)
#1285000000
1!
1)
#1290000000
0!
0)
#1295000000
1!
1)
#1300000000
0!
0)
#1305000000
1!
1)
#1310000000
0!
0)
#1315000000
1!
1)
#1320000000
0!
0)
#1325000000
1!
1#
1)
1+
#1330000000
0!
0)
#1335000000
1!
1)
b11 1
b11111111111111111111111111010111 3
#1340000000
0!
0)
#1345000000
1!
1)
b0 1
b11111111111111111111111111011000 3
#1350000000
0!
0)
#1355000000
1!
0#
1$
1)
0+
1,
b1 1
b11111111111111111111111111011001 3
#1360000000
0!
0)
#1365000000
1!
1)
b11 2
b11111111111111111111111111011000 3
#1370000000
0!
0)
#1375000000
1!
1)
b0 2
b11111111111111111111111111010111 3
#1380000000
0!
0)
#1385000000
1!
1)
b1 2
b11111111111111111111111111010110 3
#1390000000
0!
0)
#1395000000
1!
1#
0$
1)
1+
0,
b10 2
b11111111111111111111111111010101 3
#1400000000
0!
0)
#1405000000
1!
1)
b10 1
b11111111111111111111111111010110 3
#1410000000
0!
0)
#1415000000
1!
0#
1$
1)
0+
1,
b11 1
b11111111111111111111111111010111 3
#1420000000
0!
0)
#1425000000
1!
1)
b11 2
b11111111111111111111111111010110 3
#1430000000
0!
0)
#1435000000
1!
1)
b0 2
b11111111111111111111111111010101 3
#1440000000
0!
0)
#1445000000
1!
1)
b1 2
b11111111111111111111111111010100 3
#1450000000
0!
0)
#1455000000
1!
1)
b10 2
b11111111111111111111111111010011 3
#1460000000
0!
0)
#1465000000
1!
1)
b11 2
b11111111111111111111111111010010 3
#1470000000
0!
0)
#1475000000
1!
1)
b0 2
b11111111111111111111111111010001 3
#1480000000
0!
0)
#1485000000
1!
1)
b1 2
b11111111111111111111111111010000 3
#1490000000
0!
0)
#1495000000
1!
0$
1)
0,
b10 2
b11111111111111111111111111001111 3
#1500000000
0!
0)
#1505000000
1!
1)
#1510000000
0!
0)
#1515000000
1!
1)
#1520000000
0!
0)
#1525000000
1!
1)
#1530000000
0!
0)
#1535000000
1!
1)
#1540000000
0!
0)
#1545000000
1!
1#
1)
1+
#1550000000
0!
0)
#1555000000
1!
1)
b0 1
b11111111111111111111111111010000 3
#1560000000
0!
0)
#1565000000
1!
1)
b1 1
b11111111111111111111111111010001 3
#1570000000
0!
0)
#1575000000
1!
0#
1$
1)
0+
1,
b10 1
b11111111111111111111111111010010 3
#1580000000
0!
0)
#1585000000
1!
1)
b11 2
b11111111111111111111111111010001 3
#1590000000
0!
0)
#1595000000
1!
1)
b0 2
b11111111111111111111111111010000 3
#1600000000
0!
0)
#1605000000
1!
1)
b1 2
b11111111111111111111111111001111 3
#1610000000
0!
0)
#1615000000
1!
1#
0$
1)
1+
0,
b10 2
b11111111111111111111111111001110 3
#1620000000
0!
0)
#1625000000
1!
1)
b11 1
b11111111111111111111111111001111 3
#1630000000
0!
0)
#1635000000
1!
0#
1$
1)
0+
1,
b0 1
b11111111111111111111111111010000 3
#1640000000
0!
0)
#1645000000
1!
1)
b11 2
b11111111111111111111111111001111 3
#1650000000
0!
0)
#1655000000
1!
1)
b0 2
b11111111111111111111111111001110 3
#1660000000
0!
0)
#1665000000
1!
1)
b1 2
b11111111111111111111111111001101 3
#1670000000
0!
0)
#1675000000
1!
1)
b10 2
b11111111111111111111111111001100 3
#1680000000
0!
0)
#1685000000
1!
1)
b11 2
b11111111111111111111111111001011 3
#1690000000
0!
0)
#1695000000
1!
1)
b0 2
b11111111111111111111111111001010 3
#1700000000
0!
0)
#1705000000
1!
1)
b1 2
b11111111111111111111111111001001 3
#1710000000
0!
0)
#1715000000
1!
0$
1)
0,
b10 2
b11111111111111111111111111001000 3
#1720000000
0!
0)
#1725000000
1!
1)
#1730000000
0!
0)
#1735000000
1!
1)
#1740000000
0!
0)
#1745000000
1!
1)
#1750000000
0!
0)
#1755000000
1!
1)
#1760000000
0!
0)
#1765000000
1!
1#
1)
1+
#1770000000
0!
0)
#1775000000
1!
1)
b1 1
b11111111111111111111111111001001 3
#1780000000
0!
0)
#1785000000
1!
1)
b10 1
b11111111111111111111111111001010 3
#1790000000
0!
0)
#1795000000
1!
0#
1$
1)
0+
1,
b11 1
b11111111111111111111111111001011 3
#1800000000
0!
0)
#1805000000
1!
1)
b11 2
b11111111111111111111111111001010 3
#1810000000
0!
0)
#1815000000
1!
1)
b0 2
b11111111111111111111111111001001 3
#1820000000
0!
0)
#1825000000
1!
1)
b1 2
b11111111111111111111111111001000 3
#1830000000
0!
0)
#1835000000
1!
1#
0$
1)
1+
0,
b10 2
b11111111111111111111111111000111 3
#1840000000
0!
0)
#1845000000
1!
1)
b0 1
b11111111111111111111111111001000 3
#1850000000
0!
0)
#1855000000
1!
0#
1$
1)
0+
1,
b1 1
b11111111111111111111111111001001 3
#1860000000
0!
0)
#1865000000
1!
1)
b11 2
b11111111111111111111111111001000 3
#1870000000
0!
0)
#1875000000
1!
1)
b0 2
b11111111111111111111111111000111 3
#1880000000
0!
0)
#1885000000
1!
1)
b1 2
b11111111111111111111111111000110 3
#1890000000
0!
0)
#1895000000
1!
1)
b10 2
b11111111111111111111111111000101 3
#1900000000
0!
0)
#1905000000
1!
1)
b11 2
b11111111111111111111111111000100 3
#1910000000
0!
0)
#1915000000
1!
1)
b0 2
b11111111111111111111111111000011 3
#1920000000
0!
0)
#1925000000
1!
1)
b1 2
b11111111111111111111111111000010 3
#1930000000
0!
0)
#1935000000
1!
0$
1)
0,
b10 2
b11111111111111111111111111000001 3
#1940000000
0!
0)
#1945000000
1!
1)
#1950000000
0!
0)
#1955000000
1!
1)
#1960000000
0!
0)
#1965000000
1!
1)
#1970000000
0!
0)
#1975000000
1!
1)
#1980000000
0!
0)
#1985000000
1!
1#
1)
1+
#1990000000
0!
0)
#1995000000
1!
1)
b10 1
b11111111111111111111111111000010 3
#2000000000
0!
0)
#2005000000
1!
1)
b11 1
b11111111111111111111111111000011 3
#2010000000
0!
0)
#2015000000
1!
0#
1$
1)
0+
1,
b0 1
b11111111111111111111111111000100 3
#2020000000
0!
0)
#2025000000
1!
1)
b11 2
b11111111111111111111111111000011 3
#2030000000
0!
0)
#2035000000
1!
1)
b0 2
b11111111111111111111111111000010 3
#2040000000
0!
0)
#2045000000
1!
1)
b1 2
b11111111111111111111111111000001 3
#2050000000
0!
0)
#2055000000
1!
1#
0$
1)
1+
0,
b10 2
b11111111111111111111111111000000 3
#2060000000
0!
0)
#2065000000
1!
1)
b1 1
b11111111111111111111111111000001 3
#2070000000
0!
0)
#2075000000
1!
0#
1$
1)
0+
1,
b10 1
b11111111111111111111111111000010 3
#2080000000
0!
0)
#2085000000
1!
1)
b11 2
b11111111111111111111111111000001 3
#2090000000
0!
0)
#2095000000
1!
1)
b0 2
b11111111111111111111111111000000 3
#2100000000
0!
0)
#2105000000
1!
1)
b1 2
b11111111111111111111111110111111 3
#2110000000
0!
0)
#2115000000
1!
1)
b10 2
b11111111111111111111111110111110 3
#2120000000
0!
0)
#2125000000
1!
1)
b11 2
b11111111111111111111111110111101 3
#2130000000
0!
0)
#2135000000
1!
1)
b0 2
b11111111111111111111111110111100 3
#2140000000
0!
0)
#2145000000
1!
1)
b1 2
b11111111111111111111111110111011 3
#2150000000
0!
0)
#2155000000
1!
0$
1)
0,
b10 2
b11111111111111111111111110111010 3
#2160000000
0!
0)
#2165000000
1!
1)
#2170000000
0!
0)
#2175000000
1!
1)
#2180000000
0!
0)
#2185000000
1!
1)
#2190000000
0!
0)
#2195000000
1!
1)
#2200000000
0!
0)
#2205000000
1!
1#
1)
1+
#2210000000
0!
0)
#2215000000
1!
1)
b11 1
b11111111111111111111111110111011 3
#2220000000
0!
0)
#2225000000
1!
1)
b0 1
b11111111111111111111111110111100 3
#2230000000
0!
0)
#2235000000
1!
0#
1$
1)
0+
1,
b1 1
b11111111111111111111111110111101 3
#2240000000
0!
0)
#2245000000
1!
1)
b11 2
b11111111111111111111111110111100 3
#2250000000
0!
0)
#2255000000
1!
1)
b0 2
b11111111111111111111111110111011 3
#2260000000
0!
0)
#2265000000
1!
1)
b1 2
b11111111111111111111111110111010 3
#2270000000
0!
0)
#2275000000
1!
1#
0$
1)
1+
0,
b10 2
b11111111111111111111111110111001 3
#2280000000
0!
0)
#2285000000
1!
1)
b10 1
b11111111111111111111111110111010 3
#2290000000
0!
0)
#2295000000
1!
0#
1$
1)
0+
1,
b11 1
b11111111111111111111111110111011 3
#2300000000
0!
0)
#2305000000
1!
1)
b11 2
b11111111111111111111111110111010 3
#2310000000
0!
0)
#2315000000
1!
1)
b0 2
b11111111111111111111111110111001 3
#2320000000
0!
0)
#2325000000
1!
1)
b1 2
b11111111111111111111111110111000 3
#2330000000
0!
0)
#2335000000
1!
1)
b10 2
b11111111111111111111111110110111 3
#2340000000
0!
0)
#2345000000
1!
1)
b11 2
b11111111111111111111111110110110 3
#2350000000
0!
0)
#2355000000
1!
1)
b0 2
b11111111111111111111111110110101 3
#2360000000
0!
0)
#2365000000
1!
1)
b1 2
b11111111111111111111111110110100 3
#2370000000
0!
0)
#2375000000
1!
0$
1)
0,
b10 2
b11111111111111111111111110110011 3
#2380000000
0!
0)
#2385000000
1!
1)
#2390000000
0!
0)
#2395000000
1!
1)
#2400000000
0!
0)
#2405000000
1!
1)
#2410000000
0!
0)
#2415000000
1!
1)
#2420000000
0!
0)
#2425000000
1!
1#
1)
1+
#2430000000
0!
0)
#2435000000
1!
1)
b0 1
b11111111111111111111111110110100 3
#2440000000
0!
0)
#2445000000
1!
1)
b1 1
b11111111111111111111111110110101 3
#2450000000
0!
0)
#2455000000
1!
0#
1$
1)
0+
1,
b10 1
b11111111111111111111111110110110 3
#2460000000
0!
0)
#2465000000
1!
1)
b11 2
b11111111111111111111111110110101 3
#2470000000
0!
0)
#2475000000
1!
1)
b0 2
b11111111111111111111111110110100 3
#2480000000
0!
0)
#2485000000
1!
1)
b1 2
b11111111111111111111111110110011 3
#2490000000
0!
0)
#2495000000
1!
1#
0$
1)
1+
0,
b10 2
b11111111111111111111111110110010 3
#2500000000
0!
0)
#2505000000
1!
1)
b11 1
b11111111111111111111111110110011 3
#2510000000
0!
0)
#2515000000
1!
0#
1$
1)
0+
1,
b0 1
b11111111111111111111111110110100 3
#2520000000
0!
0)
#2525000000
1!
1)
b11 2
b11111111111111111111111110110011 3
#2530000000
0!
0)
#2535000000
1!
1)
b0 2
b11111111111111111111111110110010 3
#2540000000
0!
0)
#2545000000
1!
1)
b1 2
b11111111111111111111111110110001 3
#2550000000
0!
0)
#2555000000
1!
1)
b10 2
b11111111111111111111111110110000 3
#2560000000
0!
0)
#2565000000
1!
1)
b11 2
b11111111111111111111111110101111 3
#2570000000
0!
0)
#2575000000
1!
1)
b0 2
b11111111111111111111111110101110 3
#2580000000
0!
0)
#2585000000
1!
1)
b1 2
b11111111111111111111111110101101 3
#2590000000
0!
0)
#2595000000
1!
0$
1)
0,
b10 2
b11111111111111111111111110101100 3
#2600000000
0!
0)
#2605000000
1!
1)
#2610000000
0!
0)
#2615000000
1!
1)
#2620000000
0!
0)
#2625000000
1!
1)
#2630000000
0!
0)
#2635000000
1!
1)
#2640000000
0!
0)
#2645000000
1!
1#
1)
1+
#2650000000
0!
0)
#2655000000
1!
1)
b1 1
b11111111111111111111111110101101 3
#2660000000
0!
0)
#2665000000
1!
1)
b10 1
b11111111111111111111111110101110 3
#2670000000
0!
0)
#2675000000
1!
0#
1$
1)
0+
1,
b11 1
b11111111111111111111111110101111 3
#2680000000
0!
0)
#2685000000
1!
1)
b11 2
b11111111111111111111111110101110 3
#2690000000
0!
0)
#2695000000
1!
1)
b0 2
b11111111111111111111111110101101 3
#2700000000
0!
0)
#2705000000
1!
1)
b1 2
b11111111111111111111111110101100 3
#2710000000
0!
0)
#2715000000
1!
1#
0$
1)
1+
0,
b10 2
b11111111111111111111111110101011 3
#2720000000
0!
0)
#2725000000
1!
1)
b0 1
b11111111111111111111111110101100 3
#2730000000
0!
0)
#2735000000
1!
0#
1$
1)
0+
1,
b1 1
b11111111111111111111111110101101 3
#2740000000
0!
0)
#2745000000
1!
1)
b11 2
b11111111111111111111111110101100 3
#2750000000
0!
0)
#2755000000
1!
1)
b0 2
b11111111111111111111111110101011 3
#2760000000
0!
0)
#2765000000
1!
1)
b1 2
b11111111111111111111111110101010 3
#2770000000
0!
0)
#2775000000
1!
1)
b10 2
b11111111111111111111111110101001 3
#2780000000
0!
0)
#2785000000
1!
1)
b11 2
b11111111111111111111111110101000 3
#2790000000
0!
0)
#2795000000
1!
1)
b0 2
b11111111111111111111111110100111 3
#2800000000
0!
0)
#2805000000
1!
1)
b1 2
b11111111111111111111111110100110 3
#2810000000
0!
0)
#2815000000
1!
0$
1)
0,
b10 2
b11111111111111111111111110100101 3
#2820000000
0!
0)
#2825000000
1!
1)
#2830000000
0!
0)
#2835000000
1!
1)
#2840000000
0!
0)
#2845000000
1!
1)
#2850000000
0!
0)
#2855000000
1!
1)
#2860000000
0!
0)
#2865000000
1!
1#
1)
1+
#2870000000
0!
0)
#2875000000
1!
1)
b10 1
b11111111111111111111111110100110 3
#2880000000
0!
0)
#2885000000
1!
1)
b11 1
b11111111111111111111111110100111 3
#2890000000
0!
0)
#2895000000
1!
0#
1$
1)
0+
1,
b0 1
b11111111111111111111111110101000 3
#2900000000
0!
0)
#2905000000
1!
1)
b11 2
b11111111111111111111111110100111 3
#2910000000
0!
0)
#2915000000
1!
1)
b0 2
b11111111111111111111111110100110 3
#2920000000
0!
0)
