carry_lookahead_adder/full_adder.vhd
library ieee;
use ieee.std_logic_1164.all;
use ieee.numeric_std.all;

entity full_adder is
    port(
        --inputs
        i_bit_1: in std_logic;
        i_bit_0: in std_logic;
        i_carry: in std_logic;
        --outputs
        o_sum: out std_logic;
        o_carry: out std_logic
        );
end full_adder;

architecture arch of full_adder is
begin
        o_sum <= i_bit_1 xor i_bit_0 xor i_carry;
        o_carry <= (i_bit_1 and i_bit_0) or ((i_bit_1 xor i_bit_0) and i_carry);
end arch;

ripple_carry_adder/ripple_carry_adder.vhd
library ieee;
use ieee.std_logic_1164.all;

entity ripple_carry_adder is
    generic(
        g_width: natural := 2
    );
    port(
        --inputs
        i_num_1: in std_logic_vector(g_width-1 downto 0);
        i_num_0: in std_logic_vector(g_width-1 downto 0);
        --outputs
        o_result: out std_logic_vector(g_width downto 0)
    );
end ripple_carry_adder;

architecture arch of ripple_carry_adder is
    component full_adder is
        port(
            i_bit_1: in std_logic;
            i_bit_0: in std_logic;
            i_carry: in std_logic;
            o_sum: out std_logic;
            o_carry: out std_logic
        );
    end component full_adder;

    signal w_carry: std_logic_vector(g_width downto 0);
    signal w_sum: std_logic_vector(g_width-1 downto 0);

begin
    --first full_adder has no carry input
    w_carry(0) <= '0';

    generate_full_adders: for i in 0 to g_width-1 generate
        inst_full_adder: full_adder port map(
            i_bit_1 => i_num_1(i),
            i_bit_0 => i_num_0(i),
            i_carry => w_carry(i),
            o_sum => w_sum(i),
            o_carry => w_carry(i+1)
        );
    end generate generate_full_adders;

    o_result <= w_carry(g_width) & w_sum;
end arch;

ripple_carry_adder/ripple_carry_adder_tb.vhd
library ieee;
use ieee.std_logic_1164.all;

entity ripple_carry_adder_tb is
end ripple_carry_adder_tb;

architecture arch_tb of ripple_carry_adder_tb is

    constant c_width: integer := 2;

    signal r_num_1: std_logic_vector(c_width-1 downto 0) := (others => '0');
    signal r_num_0: std_logic_vector(c_width-1 downto 0) := (others => '0');
    signal w_result: std_logic_vector(c_width downto 0);

    component ripple_carry_adder is 
        generic(
            g_width: natural
        );
        port(
            i_num_1: std_logic_vector(g_width-1 downto 0);
            i_num_0: std_logic_vector(g_width-1 downto 0);
            o_result: out std_logic_vector(g_width downto 0)
        );
    end component ripple_carry_adder;

begin
    UUT: ripple_carry_adder
        generic map(
            g_width => c_width
        )
        port map(
            i_num_1 => r_num_1,
            i_num_0 => r_num_0,
            o_result => w_result
        );

    process begin
        r_num_1 <= "00";
        r_num_0 <= "01";
        wait for 10 ns;
        r_num_1 <= "10";
        r_num_0 <= "01";
        wait for 10 ns;
        r_num_1 <= "01";
        r_num_0 <= "11";
        wait for 10 ns;
        r_num_1 <= "11";
        r_num_0 <= "11";
        wait for 10 ns;
    end process;
end arch_tb;

ripple_carry_adder/ripple_carry_adder_wave.vcd
$date
  Wed Dec 29 10:10:40 2021
$end
$version
  GHDL v0
$end
$timescale
  1 fs
$end
$scope module standard $end
$upscope $end
$scope module std_logic_1164 $end
$upscope $end
$scope module numeric_std $end
$upscope $end
$scope module ripple_carry_adder_tb $end
$var reg 2 ! r_num_1[1:0] $end
$var reg 2 " r_num_0[1:0] $end
$var reg 3 # w_result[2:0] $end
$scope module uut $end
$var reg 2 $ i_num_1[1:0] $end
$var reg 2 % i_num_0[1:0] $end
$var reg 3 & o_result[2:0] $end
$var reg 3 ' w_carry[2:0] $end
$var reg 2 ( w_sum[1:0] $end
$scope module generate_full_adders(0) $end
$scope module inst_full_adder $end
$var reg 1 ) i_bit_1 $end
$var reg 1 * i_bit_0 $end
$var reg 1 + i_carry $end
$var reg 1 , o_sum $end
$var reg 1 - o_carry $end
$upscope $end
$upscope $end
$scope module generate_full_adders(1) $end
$scope module inst_full_adder $end
$var reg 1 . i_bit_1 $end
$var reg 1 / i_bit_0 $end
$var reg 1 0 i_carry $end
$var reg 1 1 o_sum $end
$var reg 1 2 o_carry $end
$upscope $end
$upscope $end
$upscope $end
$upscope $end
$enddefinitions $end
#0
b00 !
b01 "
b001 #
b00 $
b01 %
b001 &
b000 '
b01 (
0)
1*
0+
1,
0-
0.
0/
00
01
02
#10000000
b10 !
b011 #
b10 $
b011 &
b11 (
1.
11
#20000000
b01 !
b11 "
b100 #
b01 $
b11 %
b100 &
b110 '
b00 (
1)
0,
1-
0.
1/
10
01
12
#30000000
b11 !
b110 #
b11 $
b110 &
b10 (
1.
11
#40000000
b00 !
b01 "
b001 #
b00 $
b01 %
b001 &
b000 '
b01 (
0)
1,
0-
0.
0/
00
01
02
#50000000
b10 !
b011 #
b10 $
b011 &
b11 (
1.
11
#60000000
b01 !
b11 "
b100 #
b01 $
b11 %
b100 &
b110 '
b00 (
1)
0,
1-
0.
1/
10
01
12
#70000000
b11 !
b110 #
b11 $
b110 &
b10 (
1.
11
#80000000
b00 !
b01 "
b001 #
b00 $
b01 %
b001 &
b000 '
b01 (
0)
1,
0-
0.
0/
00
01
02
#90000000
b10 !
b011 #
b10 $
b011 &
b11 (
1.
11
#100000000
b01 !
b11 "
b100 #
b01 $
b11 %
b100 &
b110 '
b00 (
1)
0,
1-
0.
1/
10
01
12
#110000000
b11 !
b110 #
b11 $
b110 &
b10 (
1.
11
#120000000
b00 !
b01 "
b001 #
b00 $
b01 %
b001 &
b000 '
b01 (
0)
1,
0-
0.
0/
00
01
02
#130000000
b10 !
b011 #
b10 $
b011 &
b11 (
1.
11
#140000000
b01 !
b11 "
b100 #
b01 $
b11 %
b100 &
b110 '
b00 (
1)
0,
1-
0.
1/
10
01
12
#150000000
b11 !
b110 #
b11 $
b110 &
b10 (
1.
11
#160000000
b00 !
b01 "
b001 #
b00 $
b01 %
b001 &
b000 '
b01 (
0)
1,
0-
0.
0/
00
01
02
#170000000
b10 !
b011 #
b10 $
b011 &
b11 (
1.
11
#180000000
b01 !
b11 "
b100 #
b01 $
b11 %
b100 &
b110 '
b00 (
1)
0,
1-
0.
1/
10
01
12
#190000000
b11 !
b110 #
b11 $
b110 &
b10 (
1.
11
#200000000
b00 !
b01 "
b001 #
b00 $
b01 %
b001 &
b000 '
b01 (
0)
1,
0-
0.
0/
00
01
02
#210000000
b10 !
b011 #
b10 $
b011 &
b11 (
1.
11
#220000000
b01 !
b11 "
b100 #
b01 $
b11 %
b100 &
b110 '
b00 (
1)
0,
1-
0.
1/
10
01
12
#230000000
b11 !
b110 #
b11 $
b110 &
b10 (
1.
11
#240000000
b00 !
b01 "
b001 #
b00 $
b01 %
b001 &
b000 '
b01 (
0)
1,
0-
0.
0/
00
01
02
#250000000
b10 !
b011 #
b10 $
b011 &
b11 (
1.
11
#260000000
b01 !
b11 "
b100 #
b01 $
b11 %
b100 &
b110 '
b00 (
1)
0,
1-
0.
1/
10
01
12
#270000000
b11 !
b110 #
b11 $
b110 &
b10 (
1.
11
#280000000
b00 !
b01 "
b001 #
b00 $
b01 %
b001 &
b000 '
b01 (
0)
1,
0-
0.
0/
00
01
02
#290000000
b10 !
b011 #
b10 $
b011 &
b11 (
1.
11
#300000000
b01 !
b11 "
b100 #
b01 $
b11 %
b100 &
b110 '
b00 (
1)
0,
1-
0.
1/
10
01
12
#310000000
b11 !
b110 #
b11 $
b110 &
b10 (
1.
11
#320000000
b00 !
b01 "
b001 #
b00 $
b01 %
b001 &
b000 '
b01 (
0)
1,
0-
0.
0/
00
01
02
#330000000
b10 !
b011 #
b10 $
b011 &
b11 (
1.
11
#340000000
b01 !
b11 "
b100 #
b01 $
b11 %
b100 &
b110 '
b00 (
1)
0,
1-
0.
1/
10
01
12
#350000000
b11 !
b110 #
b11 $
b110 &
b10 (
1.
11
#360000000
b00 !
b01 "
b001 #
b00 $
b01 %
b001 &
b000 '
b01 (
0)
1,
0-
0.
0/
00
01
02
#370000000
b10 !
b011 #
b10 $
b011 &
b11 (
1.
11
#380000000
b01 !
b11 "
b100 #
b01 $
b11 %
b100 &
b110 '
b00 (
1)
0,
1-
0.
1/
10
01
12
#390000000
b11 !
b110 #
b11 $
b110 &
b10 (
1.
11
#400000000
b00 !
b01 "
b001 #
b00 $
b01 %
b001 &
b000 '
b01 (
0)
1,
0-
0.
0/
00
01
02
#410000000
b10 !
b011 #
b10 $
b011 &
b11 (
1.
11
#420000000
b01 !
b11 "
b100 #
b01 $
b11 %
b100 &
b110 '
b00 (
1)
0,
1-
0.
1/
10
01
12
#430000000
b11 !
b110 #
b11 $
b110 &
b10 (
1.
11
#440000000
b00 !
b01 "
b001 #
b00 $
b01 %
b001 &
b000 '
b01 (
0)
1,
0-
0.
0/
00
01
02
#450000000
b10 !
b011 #
b10 $
b011 &
b11 (
1.
11
#460000000
b01 !
b11 "
b100 #
b01 $
b11 %
b100 &
b110 '
b00 (
1)
0,
1-
0.
1/
10
01
12
#470000000
b11 !
b110 #
b11 $
b110 &
b10 (
1.
11
#480000000
b00 !
b01 "
b001 #
b00 $
b01 %
b001 &
b000 '
b01 (
0)
1,
0-
0.
0/
00
01
02
#490000000
b10 !
b011 #
b10 $
b011 &
b11 (
1.
11
#500000000
b01 !
b11 "
b100 #
b01 $
b11 %
b100 &
b110 '
b00 (
1)
0,
1-
0.
1/
10
01
12
#510000000
b11 !
b110 #
b11 $
b110 &
b10 (
1.
11
#520000000
b00 !
b01 "
b001 #
b00 $
b01 %
b001 &
b000 '
b01 (
0)
1,
0-
0.
0/
00
01
02
#530000000
b10 !
b011 #
b10 $
b011 &
b11 (
1.
11
#540000000
b01 !
b11 "
b100 #
b01 $
b11 %
b100 &
b110 '
b00 (
1)
0,
1-
0.
1/
10
01
12
#550000000
b11 !
b110 #
b11 $
b110 &
b10 (
1.
11
#560000000
b00 !
b01 "
b001 #
b00 $
b01 %
b001 &
b000 '
b01 (
0)
1,
0-
0.
0/
00
01
02
#570000000
b10 !
b011 #
b10 $
b011 &
b11 (
1.
11
#580000000
b01 !
b11 "
b100 #
b01 $
b11 %
b100 &
b110 '
b00 (
1)
0,
1-
0.
1/
10
01
12
#590000000
b11 !
b110 #
b11 $
b110 &
b10 (
1.
11
#600000000
b00 !
b01 "
b001 #
b00 $
b01 %
b001 &
b000 '
b01 (
0)
1,
0-
0.
0/
00
01
02
#610000000
b10 !
b011 #
b10 $
b011 &
b11 (
1.
11
#620000000
b01 !
b11 "
b100 #
b01 $
b11 %
b100 &
b110 '
b00 (
1)
0,
1-
0.
1/
10
01
12
#630000000
b11 !
b110 #
b11 $
b110 &
b10 (
1.
11
#640000000
b00 !
b01 "
b001 #
b00 $
b01 %
b001 &
b000 '
b01 (
0)
1,
0-
0.
0/
00
01
02
#650000000
b10 !
b011 #
b10 $
b011 &
b11 (
1.
11
#660000000
b01 !
b11 "
b100 #
b01 $
b11 %
b100 &
b110 '
b00 (
1)
0,
1-
0.
1/
10
01
12
#670000000
b11 !
b110 #
b11 $
b110 &
b10 (
1.
11
#680000000
b00 !
b01 "
b001 #
b00 $
b01 %
b001 &
b000 '
b01 (
0)
1,
0-
0.
0/
00
01
02
#690000000
b10 !
b011 #
b10 $
b011 &
b11 (
1.
11
#700000000
b01 !
b11 "
b100 #
b01 $
b11 %
b100 &
b110 '
b00 (
1)
0,
1-
0.
1/
10
01
12
#710000000
b11 !
b110 #
b11 $
b110 &
b10 (
1.
11
#720000000
b00 !
b01 "
b001 #
b00 $
b01 %
b001 &
b000 '
b01 (
0)
1,
0-
0.
0/
00
01
02
#730000000
b10 !
b011 #
b10 $
b011 &
b11 (
1.
11
#740000000
b01 !
b11 "
b100 #
b01 $
b11 %
b100 &
b110 '
b00 (
1)
0,
1-
0.
1/
10
01
12
#750000000
b11 !
b110 #
b11 $
b110 &
b10 (
1.
11
#760000000
b00 !
b01 "
b001 #
b00 $
b01 %
b001 &
b000 '
b01 (
0)
1,
0-
0.
0/
00
01
02
#770000000
b10 !
b011 #
b10 $
b011 &
b11 (
1.
11
#780000000
b01 !
b11 "
b100 #
b01 $
b11 %
b100 &
b110 '
b00 (
1)
0,
1-
0.
1/
10
01
12
#790000000
b11 !
b110 #
b11 $
b110 &
b10 (
1.
11
#800000000
b00 !
b01 "
b001 #
b00 $
b01 %
b001 &
b000 '
b01 (
0)
1,
0-
0.
0/
00
01
02
#810000000
b10 !
b011 #
b10 $
b011 &
b11 (
1.
11
#820000000
b01 !
b11 "
b100 #
b01 $
b11 %
b100 &
b110 '
b00 (
1)
0,
1-
0.
1/
10
01
12
#830000000
b11 !
b110 #
b11 $
b110 &
b10 (
1.
11
#840000000
b00 !
b01 "
b001 #
b00 $
b01 %
b001 &
b000 '
b01 (
0)
1,
0-
0.
0/
00
01
02
#850000000
b10 !
b011 #
b10 $
b011 &
b11 (
1.
11
#860000000
b01 !
b11 "
b100 #
b01 $
b11 %
b100 &
b110 '
b00 (
1)
0,
1-
0.
1/
10
01
12
#870000000
b11 !
b110 #
b11 $
b110 &
b10 (
1.
11
#880000000
b00 !
b01 "
b001 #
b00 $
b01 %
b001 &
b000 '
b01 (
0)
1,
0-
0.
0/
00
01
02
#890000000
b10 !
b011 #
b10 $
b011 &
b11 (
1.
11
#900000000
b01 !
b11 "
b100 #
b01 $
b11 %
b100 &
b110 '
b00 (
1)
0,
1-
0.
1/
10
01
12
#910000000
b11 !
b110 #
b11 $
b110 &
b10 (
1.
11
#920000000
b00 !
b01 "
b001 #
b00 $
b01 %
b001 &
b000 '
b01 (
0)
1,
0-
0.
0/
00
01
02
#930000000
b10 !
b011 #
b10 $
b011 &
b11 (
1.
11
#940000000
b01 !
b11 "
b100 #
b01 $
b11 %
b100 &
b110 '
b00 (
1)
0,
1-
0.
1/
10
01
12
#950000000
b11 !
b110 #
b11 $
b110 &
b10 (
1.
11
#960000000
b00 !
b01 "
b001 #
b00 $
b01 %
b001 &
b000 '
b01 (
0)
1,
0-
0.
0/
00
01
02
#970000000
b10 !
b011 #
b10 $
b011 &
b11 (
1.
11
#980000000
b01 !
b11 "
b100 #
b01 $
b11 %
b100 &
b110 '
b00 (
1)
0,
1-
0.
1/
10
01
12
#990000000
b11 !
b110 #
b11 $
b110 &
b10 (
1.
11
#1000000000
b00 !
b01 "
b001 #
b00 $
b01 %
b001 &
b000 '
b01 (
0)
1,
0-
0.
0/
00
01
02
#1010000000
b10 !
b011 #
b10 $
b011 &
b11 (
1.
11
#1020000000
b01 !
b11 "
b100 #
b01 $
b11 %
b100 &
b110 '
b00 (
1)
0,
1-
0.
1/
10
01
12
#1030000000
b11 !
b110 #
b11 $
b110 &
b10 (
1.
11
#1040000000
b00 !
b01 "
b001 #
b00 $
b01 %
b001 &
b000 '
b01 (
0)
1,
0-
0.
0/
00
01
02
#1050000000
b10 !
b011 #
b10 $
b011 &
b11 (
1.
11
#1060000000
b01 !
b11 "
b100 #
b01 $
b11 %
b100 &
b110 '
b00 (
1)
0,
1-
0.
1/
10
01
12
#1070000000
b11 !
b110 #
b11 $
b110 &
b10 (
1.
11
#1080000000
b00 !
b01 "
b001 #
b00 $
b01 %
b001 &
b000 '
b01 (
0)
1,
0-
0.
0/
00
01
02
#1090000000
b10 !
b011 #
b10 $
b011 &
b11 (
1.
11
#1100000000
b01 !
b11 "
b100 #
b01 $
b11 %
b100 &
b110 '
b00 (
1)
0,
1-
0.
1/
10
01
12
#1110000000
b11 !
b110 #
b11 $
b110 &
b10 (
1.
11
#1120000000
b00 !
b01 "
b001 #
b00 $
b01 %
b001 &
b000 '
b01 (
0)
1,
0-
0.
0/
00
01
02
#1130000000
b10 !
b011 #
b10 $
b011 &
b11 (
1.
11
#1140000000
b01 !
b11 "
b100 #
b01 $
b11 %
b100 &
b110 '
b00 (
1)
0,
1-
0.
1/
10
01
12
#1150000000
b11 !
b110 #
b11 $
b110 &
b10 (
1.
11
#1160000000
b00 !
b01 "
b001 #
b00 $
b01 %
b001 &
b000 '
b01 (
0)
1,
0-
0.
0/
00
01
02
#1170000000
b10 !
b011 #
b10 $
b011 &
b11 (
1.
11
#1180000000
b01 !
b11 "
b100 #
b01 $
b11 %
b100 &
b110 '
b00 (
1)
0,
1-
0.
1/
10
01
12
#1190000000
b11 !
b110 #
b11 $
b110 &
b10 (
1.
11
#1200000000
b00 !
b01 "
b001 #
b00 $
b01 %
b001 &
b000 '
b01 (
0)
1,
0-
0.
0/
00
01
02
#1210000000
b10 !
b011 #
b10 $
b011 &
b11 (
1.
11
#1220000000
b01 !
b11 "
b100 #
b01 $
b11 %
b100 &
b110 '
b00 (
1)
0,
1-
0.
1/
10
01
12
#1230000000
b11 !
b110 #
b11 $
b110 &
b10 (
1.
11
#1240000000
b00 !
b01 "
b001 #
b00 $
b01 %
b001 &
b000 '
b01 (
0)
1,
0-
0.
0/
00
01
02
#1250000000
b10 !
b011 #
b10 $
b011 &
b11 (
1.
11
#1260000000
b01 !
b11 "
b100 #
b01 $
b11 %
b100 &
b110 '
b00 (
1)
0,
1-
0.
1/
10
01
12
#1270000000
b11 !
b110 #
b11 $
b110 &
b10 (
1.
11
#1280000000
b00 !
b01 "
b001 #
b00 $
b01 %
b001 &
b000 '
b01 (
0)
1,
0-
0.
0/
00
01
02
#1290000000
b10 !
b011 #
b10 $
b011 &
b11 (
1.
11
#1300000000
b01 !
b11 "
b100 #
b01 $
b11 %
b100 &
b110 '
b00 (
1)
0,
1-
0.
1/
10
01
12
#1310000000
b11 !
b110 #
b11 $
b110 &
b10 (
1.
11
#1320000000
b00 !
b01 "
b001 #
b00 $
b01 %
b001 &
b000 '
b01 (
0)
1,
0-
0.
0/
00
01
02
#1330000000
b10 !
b011 #
b10 $
b011 &
b11 (
1.
11
#1340000000
b01 !
b11 "
b100 #
b01 $
b11 %
b100 &
b110 '
b00 (
1)
0,
1-
0.
1/
10
01
12
#1350000000
b11 !
b110 #
b11 $
b110 &
b10 (
1.
11
#1360000000
b00 !
b01 "
b001 #
b00 $
b01 %
b001 &
b000 '
b01 (
0)
1,
0-
0.
0/
00
01
02
#1370000000
b10 !
b011 #
b10 $
b011 &
b11 (
1.
11
#1380000000
b01 !
b11 "
b100 #
b01 $
b11 %
b100 &
b110 '
b00 (
1)
0,
1-
0.
1/
10
01
12
#1390000000
b11 !
b110 #
b11 $
b110 &
b10 (
1.
11
#1400000000
b00 !
b01 "
b001 #
b00 $
b01 %
b001 &
b000 '
b01 (
0)
1,
0-
0.
0/
00
01
02
#1410000000
b10 !
b011 #
b10 $
b011 &
b11 (
1.
11
#1420000000
b01 !
b11 "
b100 #
b01 $
b11 %
b100 &
b110 '
b00 (
1)
0,
1-
0.
1/
10
01
12
#1430000000
b11 !
b110 #
b11 $
b110 &
b10 (
1.
11
#1440000000
b00 !
b01 "
b001 #
b00 $
b01 %
b001 &
b000 '
b01 (
0)
1,
0-
0.
0/
00
01
02
#1450000000
b10 !
b011 #
b10 $
b011 &
b11 (
1.
11
#1460000000
b01 !
b11 "
b100 #
b01 $
b11 %
b100 &
b110 '
b00 (
1)
0,
1-
0.
1/
10
01
12
#1470000000
b11 !
b110 #
b11 $
b110 &
b10 (
1.
11
#1480000000
b00 !
b01 "
b001 #
b00 $
b01 %
b001 &
b000 '
b01 (
0)
1,
0-
0.
0/
00
01
02
#1490000000
b10 !
b011 #
b10 $
b011 &
b11 (
1.
11
#1500000000
b01 !
b11 "
b100 #
b01 $
b11 %
b100 &
b110 '
b00 (
1)
0,
1-
0.
1/
10
01
12
#1510000000
b11 !
b110 #
b11 $
b110 &
b10 (
1.
11
#1520000000
b00 !
b01 "
b001 #
b00 $
b01 %
b001 &
b000 '
b01 (
0)
1,
0-
0.
0/
00
01
02
#1530000000
b10 !
b011 #
b10 $
b011 &
b11 (
1.
11
#1540000000
b01 !
b11 "
b100 #
b01 $
b11 %
b100 &
b110 '
b00 (
1)
0,
1-
0.
1/
10
01
12
#1550000000
b11 !
b110 #
b11 $
b110 &
b10 (
1.
11
#1560000000
b00 !
b01 "
b001 #
b00 $
b01 %
b001 &
b000 '
b01 (
0)
1,
0-
0.
0/
00
01
02
#1570000000
b10 !
b011 #
b10 $
b011 &
b11 (
1.
11
#1580000000
b01 !
b11 "
b100 #
b01 $
b11 %
b100 &
b110 '
b00 (
1)
0,
1-
0.
1/
10
01
12
#1590000000
b11 !
b110 #
b11 $
b110 &
b10 (
1.
11
#1600000000
b00 !
b01 "
b001 #
b00 $
b01 %
b001 &
b000 '
b01 (
0)
1,
0-
0.
0/
00
01
02
#1610000000
b10 !
b011 #
b10 $
b011 &
b11 (
1.
11
#1620000000
b01 !
b11 "
b100 #
b01 $
b11 %
b100 &
b110 '
b00 (
1)
0,
1-
0.
1/
10
01
12
#1630000000
b11 !
b110 #
b11 $
b110 &
b10 (
1.
11
#1640000000
b00 !
b01 "
b001 #
b00 $
b01 %
b001 &
b000 '
b01 (
0)
1,
0-
0.
0/
00
01
02
#1650000000
b10 !
b011 #
b10 $
b011 &
b11 (
1.
11
#1660000000
b01 !
b11 "
b100 #
b01 $
b11 %
b100 &
b110 '
b00 (
1)
0,
1-
0.
1/
10
01
12
#1670000000
b11 !
b110 #
b11 $
b110 &
b10 (
1.
11
#1680000000
b00 !
b01 "
b001 #
b00 $
b01 %
b001 &
b000 '
b01 (
0)
1,
0-
0.
0/
00
01
02
#1690000000
b10 !
b011 #
b10 $
b011 &
b11 (
1.
11
#1700000000
b01 !
b11 "
b100 #
b01 $
b11 %
b100 &
b110 '
b00 (
1)
0,
1-
0.
1/
10
01
12
#1710000000
b11 !
b110 #
b11 $
b110 &
b10 (
1.
11
#1720000000
b00 !
b01 "
b001 #
b00 $
b01 %
b001 &
b000 '
b01 (
0)
1,
0-
0.
0/
00
01
02
#1730000000
b10 !
b011 #
b10 $
b011 &
b11 (
1.
11
#1740000000
b01 !
b11 "
b100 #
b01 $
b11 %
b100 &
b110 '
b00 (
1)
0,
1-
0.
1/
10
01
12
#1750000000
b11 !
b110 #
b11 $
b110 &
b10 (
1.
11
#1760000000
b00 !
b01 "
b001 #
b00 $
b01 %
b001 &
b000 '
b01 (
0)
1,
0-
0.
0/
00
01
02
#1770000000
b10 !
b011 #
b10 $
b011 &
b11 (
1.
11
#1780000000
b01 !
b11 "
b100 #
b01 $
b11 %
b100 &
b110 '
b00 (
1)
0,
1-
0.
1/
10
01
12
#1790000000
b11 !
b110 #
b11 $
b110 &
b10 (
1.
11
#1800000000
b00 !
b01 "
b001 #
b00 $
b01 %
b001 &
b000 '
b01 (
0)
1,
0-
0.
0/
00
01
02
#1810000000
b10 !
b011 #
b10 $
b011 &
b11 (
1.
11
#1820000000
b01 !
b11 "
b100 #
b01 $
b11 %
b100 &
b110 '
b00 (
1)
0,
1-
0.
1/
10
01
12
#1830000000
b11 !
b110 #
b11 $
b110 &
b10 (
1.
11
#1840000000
b00 !
b01 "
b001 #
b00 $
b01 %
b001 &
b000 '
b01 (
0)
1,
0-
0.
0/
00
01
02
#1850000000
b10 !
b011 #
b10 $
b011 &
b11 (
1.
11
#1860000000
b01 !
b11 "
b100 #
b01 $
b11 %
b100 &
b110 '
b00 (
1)
0,
1-
0.
1/
10
01
12
#1870000000
b11 !
b110 #
b11 $
b110 &
b10 (
1.
11
#1880000000
b00 !
b01 "
b001 #
b00 $
b01 %
b001 &
b000 '
b01 (
0)
1,
0-
0.
0/
00
01
02
#1890000000
b10 !
b011 #
b10 $
b011 &
b11 (
1.
11
#1900000000
b01 !
b11 "
b100 #
b01 $
b11 %
b100 &
b110 '
b00 (
1)
0,
1-
0.
1/
10
01
12
#1910000000
b11 !
b110 #
b11 $
b110 &
b10 (
1.
11
#1920000000
b00 !
b01 "
b001 #
b00 $
b01 %
b001 &
b000 '
b01 (
0)
1,
0-
0.
0/
00
01
02
#1930000000
b10 !
b011 #
b10 $
b011 &
b11 (
1.
11
#1940000000
b01 !
b11 "
b100 #
b01 $
b11 %
b100 &
b110 '
b00 (
1)
0,
1-
0.
1/
10
01
12
#1950000000
b11 !
b110 #
b11 $
b110 &
b10 (
1.
11
#1960000000
b00 !
b01 "
b001 #
b00 $
b01 %
b001 &
b000 '
b01 (
0)
1,
0-
0.
0/
00
01
02
#1970000000
b10 !
b011 #
b10 $
b011 &
b11 (
1.
11
#1980000000
b01 !
b11 "
b100 #
b01 $
b11 %
b100 &
b110 '
b00 (
1)
0,
1-
0.
1/
10
01
12
#1990000000
b11 !
b110 #
b11 $
b110 &
b10 (
1.
11
#2000000000
b00 !
b01 "
b001 #
b00 $
b01 %
b001 &
b000 '
b01 (
0)
1,
0-
0.
0/
00
01
02
#2010000000
b10 !
b011 #
b10 $
b011 &
b11 (
1.
11
#2020000000
b01 !
b11 "
b100 #
b01 $
b11 %
b100 &
b110 '
b00 (
1)
0,
1-
0.
1/
10
01
12
#2030000000
b11 !
b110 #
b11 $
b110 &
b10 (
1.
11
#2040000000
b00 !
b01 "
b001 #
b00 $
b01 %
b001 &
b000 '
b01 (
0)
1,
0-
0.
0/
00
01
02
#2050000000
b10 !
b011 #
b10 $
b011 &
b11 (
1.
11
#2060000000
b01 !
b11 "
b100 #
b01 $
b11 %
b100 &
b110 '
b00 (
1)
0,
1-
0.
1/
10
01
12
#2070000000
b11 !
b110 #
b11 $
b110 &
b10 (
1.
11
#2080000000
b00 !
b01 "
b001 #
b00 $
b01 %
b001 &
b000 '
b01 (
0)
1,
0-
0.
0/
00
01
02
#2090000000
b10 !
b011 #
b10 $
b011 &
b11 (
1.
11
#2100000000
b01 !
b11 "
b100 #
b01 $
b11 %
b100 &
b110 '
b00 (
1)
0,
1-
0.
1/
10
01
12
#2110000000
b11 !
b110 #
b11 $
b110 &
b10 (
1.
11
#2120000000
b00 !
b01 "
b001 #
b00 $
b01 %
b001 &
b000 '
b01 (
0)
1,
0-
0.
0/
00
01
02
#2130000000
b10 !
b011 #
b10 $
b011 &
b11 (
1.
11
#2140000000
b01 !
b11 "
b100 #
b01 $
b11 %
b100 &
b110 '
b00 (
1)
0,
1-
0.
1/
10
01
12
#2150000000
b11 !
b110 #
b11 $
b110 &
b10 (
1.
11
#2160000000
b00 !
b01 "
b001 #
b00 $
b01 %
b001 &
b000 '
b01 (
0)
1,
0-
0.
0/
00
01
02
#2170000000
b10 !
b011 #
b10 $
b011 &
b11 (
1.
11
#2180000000
b01 !
b11 "
b100 #
b01 $
b11 %
b100 &
b110 '
b00 (
1)
0,
1-
0.
1/
10
01
12
#2190000000
b11 !
b110 #
b11 $
b110 &
b10 (
1.
11
#2200000000
b00 !
b01 "
b001 #
b00 $
b01 %
b001 &
b000 '
b01 (
0)
1,
0-
0.
0/
00
01
02
#2210000000
b10 !
b011 #
b10 $
b011 &
b11 (
1.
11
#2220000000
b01 !
b11 "
b100 #
b01 $
b11 %
b100 &
b110 '
b00 (
1)
0,
1-
0.
1/
10
01
12
#2230000000
b11 !
b110 #
b11 $
b110 &
b10 (
1.
11
#2240000000
b00 !
b01 "
b001 #
b00 $
b01 %
b001 &
b000 '
b01 (
0)
1,
0-
0.
0/
00
01
02
#2250000000
b10 !
b011 #
b10 $
b011 &
b11 (
1.
11
#2260000000
b01 !
b11 "
b100 #
b01 $
b11 %
b100 &
b110 '
b00 (
1)
0,
1-
0.
1/
10
01
12
#2270000000
b11 !
b110 #
b11 $
b110 &
b10 (
1.
11
#2280000000
b00 !
b01 "
b001 #
b00 $
b01 %
b001 &
b000 '
b01 (
0)
1,
0-
0.
0/
00
01
02
#2290000000
b10 !
b011 #
b10 $
b011 &
b11 (
1.
11
#2300000000
b01 !
b11 "
b100 #
b01 $
b11 %
b100 &
b110 '
b00 (
1)
0,
1-
0.
1/
10
01
12
#2310000000
b11 !
b110 #
b11 $
b110 &
b10 (
1.
11
#2320000000
b00 !
b01 "
b001 #
b00 $
b01 %
b001 &
b000 '
b01 (
0)
1,
0-
0.
0/
00
01
02
#2330000000
b10 !
b011 #
b10 $
b011 &
b11 (
1.
11
#2340000000
b01 !
b11 "
b100 #
b01 $
b11 %
b100 &
b110 '
b00 (
1)
0,
1-
0.
1/
10
01
12
#2350000000
b11 !
b110 #
b11 $
b110 &
b10 (
1.
11
#2360000000
b00 !
b01 "
b001 #
b00 $
b01 %
b001 &
b000 '
b01 (
0)
1,
0-
0.
0/
00
01
02
#2370000000
b10 !
b011 #
b10 $
b011 &
b11 (
1.
11
#2380000000
b01 !
b11 "
b100 #
b01 $
b11 %
b100 &
b110 '
b00 (
1)
0,
1-
0.
1/
10
01
12
#2390000000
b11 !
b110 #
b11 $
b110 &
b10 (
1.
11
#2400000000
b00 !
b01 "
b001 #
b00 $
b01 %
b001 &
b000 '
b01 (
0)
1,
0-
0.
0/
00
01
02
#2410000000
b10 !
b011 #
b10 $
b011 &
b11 (
1.
11
#2420000000
b01 !
b11 "
b100 #
b01 $
b11 %
b100 &
b110 '
b00 (
1)
0,
1-
0.
1/
10
01
12
#2430000000
b11 !
b110 #
b11 $
b110 &
b10 (
1.
11
#2440000000
b00 !
b01 "
b001 #
b00 $
b01 %
b001 &
b000 '
b01 (
0)
1,
0-
0.
0/
00
01
02
#2450000000
b10 !
b011 #
b10 $
b011 &
b11 (
1.
11
#2460000000
b01 !
b11 "
b100 #
b01 $
b11 %
b100 &
b110 '
b00 (
1)
0,
1-
0.
1/
10
01
12
#2470000000
b11 !
b110 #
b11 $
b110 &
b10 (
1.
11
#2480000000
b00 !
b01 "
b001 #
b00 $
b01 %
b001 &
b000 '
b01 (
0)
1,
0-
0.
0/
00
01
02
#2490000000
b10 !
b011 #
b10 $
b011 &
b11 (
1.
11
#2500000000
b01 !
b11 "
b100 #
b01 $
b11 %
b100 &
b110 '
b00 (
1)
0,
1-
0.
1/
10
01
12
#2510000000
b11 !
b110 #
b11 $
b110 &
b10 (
1.
11
#2520000000
b00 !
b01 "
b001 #
b00 $
b01 %
b001 &
b000 '
b01 (
0)
1,
0-
0.
0/
00
01
02
#2530000000
b10 !
b011 #
b10 $
b011 &
b11 (
1.
11
